[
 {
   "brand": "KNOWN SUPPLY",
   "avg_brand_rating": "2.85"
 },
 {
   "brand": "AMENDI",
   "avg_brand_rating": "3.233333333333333"
 },
 {
   "brand": "SANVT",
   "avg_brand_rating": "1.7"
 },
 {
   "brand": "Patagonia",
   "avg_brand_rating": "4.333333333333333"
 },
 {
   "brand": "Scotch & Soda",
   "avg_brand_rating": "3.3"
 },
 {
   "brand": "KINdom",
   "avg_brand_rating": "1.7"
 },
 {
   "brand": "Ecoalf",
   "avg_brand_rating": "2.85"
 },
 {
   "brand": "Unspun",
   "avg_brand_rating": "3.9"
 },
 {
   "brand": "Pangaia",
   "avg_brand_rating": "3.766666666666667"
 },
 {
   "brand": "Po-Zu",
   "avg_brand_rating": "2.85"
 },
 {
   "brand": "Taylor Stitch",
   "avg_brand_rating": "3.15"
 },
 {
   "brand": "Selfmade",
   "avg_brand_rating": "3.3"
 },
 {
   "brand": "Wolven",
   "avg_brand_rating": "3.233333333333333"
 },
 {
   "brand": "People Tree",
   "avg_brand_rating": "3.9"
 },
 {
   "brand": "DillySocks",
   "avg_brand_rating": "3.233333333333333"
 },
 {
   "brand": "Thousand Fell",
   "avg_brand_rating": "1.7"
 },
 {
   "brand": "The Good Tee",
   "avg_brand_rating": "5.0"
 },
 {
   "brand": "Reprise",
   "avg_brand_rating": "1.7"
 },
 {
   "brand": "CHNGE",
   "avg_brand_rating": "3.766666666666667"
 },
 {
   "brand": "Pact",
   "avg_brand_rating": "3.766666666666667"
 },
 {
   "brand": "Girlfriend Collective",
   "avg_brand_rating": "3.766666666666667"
 },
 {
   "brand": "prAna",
   "avg_brand_rating": "2.35"
 },
 {
   "brand": "Conscious Step",
   "avg_brand_rating": "2.85"
 },
 {
   "brand": "NAADAM",
   "avg_brand_rating": "2.35"
 },
 {
   "brand": "Save the Duck",
   "avg_brand_rating": "3.15"
 },
 {
   "brand": "EDWIN",
   "avg_brand_rating": "1.7"
 },
 {
   "brand": "Kozm",
   "avg_brand_rating": "1.7"
 },
 {
   "brand": "Adelante Made-to-Order",
   "avg_brand_rating": "5.0"
 },
 {
   "brand": "Coalatree",
   "avg_brand_rating": "3.15"
 },
 {
   "brand": "The Classic T-Shirt Company",
   "avg_brand_rating": "2.85"
 },
 {
   "brand": "SOKO",
   "avg_brand_rating": "3.3"
 },
 {
   "brand": "Frankie Collective",
   "avg_brand_rating": "2.85"
 },
 {
   "brand": "Brilliant Earth",
   "avg_brand_rating": "1.7"
 },
 {
   "brand": "Whimsy + Row",
   "avg_brand_rating": "3.766666666666667"
 },
 {
   "brand": "Triarchy",
   "avg_brand_rating": "4.433333333333334"
 },
 {
   "brand": "Ecologyst",
   "avg_brand_rating": "3.3"
 },
 {
   "brand": "Astor & Orion",
   "avg_brand_rating": "1.7"
 },
 {
   "brand": "Reformation",
   "avg_brand_rating": "3.233333333333333"
 },
 {
   "brand": "Nisolo",
   "avg_brand_rating": "2.85"
 },
 {
   "brand": "Colorful Standard",
   "avg_brand_rating": "3.766666666666667"
 },
 {
   "brand": "GOEX Apparel",
   "avg_brand_rating": "1.7"
 },
 {
   "brand": "Beckett Simonon",
   "avg_brand_rating": "3.3"
 },
 {
   "brand": "ADIFF",
   "avg_brand_rating": "3.3"
 },
 {
   "brand": "Filippa K",
   "avg_brand_rating": "1.7"
 },
 {
   "brand": "Kuyichi Pure Goods",
   "avg_brand_rating": "5.0"
 },
 {
   "brand": "Parker Clay",
   "avg_brand_rating": "2.85"
 },
 {
   "brand": "Dedicated",
   "avg_brand_rating": "3.9"
 },
 {
   "brand": "AlterX Co.",
   "avg_brand_rating": "3.3"
 },
 {
   "brand": "BAM Bamboo Clothing",
   "avg_brand_rating": "2.85"
 },
 {
   "brand": "culthread",
   "avg_brand_rating": "5.0"
 },
 {
   "brand": "Koio",
   "avg_brand_rating": "2.35"
 },
 {
   "brand": "Tentree",
   "avg_brand_rating": "3.766666666666667"
 },
 {
   "brand": "Kotn",
   "avg_brand_rating": "3.766666666666667"
 },
 {
   "brand": "Zero Waste Daniel",
   "avg_brand_rating": "4.333333333333333"
 },
 {
   "brand": "Ninety Percent",
   "avg_brand_rating": "3.766666666666667"
 },
 {
   "brand": "Cotopaxi",
   "avg_brand_rating": "3.233333333333333"
 },
 {
   "brand": "ETRE Organic Underwear",
   "avg_brand_rating": "1.7"
 },
 {
   "brand": "Boyish Jeans",
   "avg_brand_rating": "5.0"
 },
 {
   "brand": "United by Blue",
   "avg_brand_rating": "2.85"
 },
 {
   "brand": "Nudie Jeans",
   "avg_brand_rating": "5.0"
 },
 {
   "brand": "Organic Basics",
   "avg_brand_rating": "3.9"
 },
 {
   "brand": "Suit Supply",
   "avg_brand_rating": "3.3"
 },
 {
   "brand": "Frank & Oak",
   "avg_brand_rating": "1.7"
 },
 {
   "brand": "ISTO",
   "avg_brand_rating": "2.85"
 },
 {
   "brand": "Subset",
   "avg_brand_rating": "5.0"
 },
 {
   "brand": "MATE the Label",
   "avg_brand_rating": "3.766666666666667"
 },
 {
   "brand": "Iron Roots",
   "avg_brand_rating": "3.9"
 },
 {
   "brand": "Warby Parker",
   "avg_brand_rating": "1.7"
 },
 {
   "brand": "Finisterre",
   "avg_brand_rating": "3.233333333333333"
 },
 {
   "brand": "Fite Fashion",
   "avg_brand_rating": "1.7"
 },
 {
   "brand": "Icebreaker",
   "avg_brand_rating": "2.566666666666667"
 },
 {
   "brand": "MUD Jeans",
   "avg_brand_rating": "5.0"
 },
 {
   "brand": "Arvin Goods",
   "avg_brand_rating": "1.7"
 },
 {
   "brand": "Toad&Co",
   "avg_brand_rating": "3.65"
 },
 {
   "brand": "Voyce Threads",
   "avg_brand_rating": "1.7"
 },
 {
   "brand": "Ten Thousand Villages",
   "avg_brand_rating": "1.7"
 },
 {
   "brand": "Groceries Apparel",
   "avg_brand_rating": "2.85"
 },
 {
   "brand": "OSOM",
   "avg_brand_rating": "1.7"
 },
 {
   "brand": "No Nasties",
   "avg_brand_rating": "5.0"
 },
 {
   "brand": "8000Kicks",
   "avg_brand_rating": "1.7"
 },
 {
   "brand": "Ministry of Supply",
   "avg_brand_rating": "2.85"
 },
 {
   "brand": "Topiku",
   "avg_brand_rating": "3.3"
 },
 {
   "brand": "Liila",
   "avg_brand_rating": "1.7"
 },
 {
   "brand": "Up-fuse",
   "avg_brand_rating": "4.5"
 },
 {
   "brand": "Outerknown",
   "avg_brand_rating": "4.333333333333333"
 },
 {
   "brand": "Etiko",
   "avg_brand_rating": "5.0"
 },
 {
   "brand": "Hernest Project",
   "avg_brand_rating": "3.233333333333333"
 },
 {
   "brand": "PANAFRICA",
   "avg_brand_rating": "2.85"
 },
 {
   "brand": "Teemill",
   "avg_brand_rating": "3.35"
 },
 {
   "brand": "Veja",
   "avg_brand_rating": "2.85"
 },
 {
   "brand": "Lucy & Yak",
   "avg_brand_rating": "4.333333333333333"
 },
 {
   "brand": "Marimekko",
   "avg_brand_rating": "1.7"
 },
 {
   "brand": "Asket",
   "avg_brand_rating": "3.233333333333333"
 },
 {
   "brand": "Burning Heart",
   "avg_brand_rating": "3.3"
 },
 {
   "brand": "Vustra",
   "avg_brand_rating": "1.7"
 },
 {
   "brand": "Rozenbroek",
   "avg_brand_rating": "3.5666666666666664"
 },
 {
   "brand": "ARMEDANGELS",
   "avg_brand_rating": "3.9"
 },
 {
   "brand": "TAMGA",
   "avg_brand_rating": "3.3"
 },
 {
   "brand": "Outland Denim",
   "avg_brand_rating": "5.0"
 },
 {
   "brand": "Kowtow",
   "avg_brand_rating": "3.766666666666667"
 },
 {
   "brand": "Stella McCartney",
   "avg_brand_rating": "3.233333333333333"
 },
 {
   "brand": "Indigenous",
   "avg_brand_rating": "3.65"
 },
 {
   "brand": "AARVEN",
   "avg_brand_rating": "4.0"
 },
 {
   "brand": "A A K S",
   "avg_brand_rating": "4.0"
 },
 {
   "brand": "Aestethic London",
   "avg_brand_rating": "5.0"
 },
 {
   "brand": "A-dam",
   "avg_brand_rating": "4.0"
 },
 {
   "brand": "Adele Dejak",
   "avg_brand_rating": "3.0"
 },
 {
   "brand": "Absolutely Bear",
   "avg_brand_rating": "4.0"
 },
 {
   "brand": "Adarche Clothing",
   "avg_brand_rating": "4.0"
 },
 {
   "brand": "A.BCH",
   "avg_brand_rating": "5.0"
 },
 {
   "brand": "AFROBLONDE",
   "avg_brand_rating": "4.0"
 },
 {
   "brand": "(di)vision",
   "avg_brand_rating": "4.0"
 },
 {
   "brand": "ACBC",
   "avg_brand_rating": "3.0"
 },
 {
   "brand": "A. ROEGE HOVE",
   "avg_brand_rating": "4.0"
 },
 {
   "brand": "A_C",
   "avg_brand_rating": "4.0"
 },
 {
   "brand": "AEANCE",
   "avg_brand_rating": "4.0"
 },
 {
   "brand": "AERA",
   "avg_brand_rating": "4.0"
 },
 {
   "brand": "Adidas",
   "avg_brand_rating": "2.5"
 },
 {
   "brand": "About Companions",
   "avg_brand_rating": "4.0"
 },
 {
   "brand": "A Happy Brand",
   "avg_brand_rating": "4.0"
 },
 {
   "brand": "Les Sublimes",
   "avg_brand_rating": "4.0"
 },
 {
   "brand": "[eyd]",
   "avg_brand_rating": "4.0"
 },
 {
   "brand": "7PLIS",
   "avg_brand_rating": "4.0"
 },
 {
   "brand": "A Natural Connection",
   "avg_brand_rating": "3.5"
 },
 {
   "brand": "337 BRAND",
   "avg_brand_rating": "4.0"
 },
 {
   "brand": "AGMES",
   "avg_brand_rating": "4.0"
 },
 {
   "brand": "Adelaide C. Ecoage",
   "avg_brand_rating": "4.0"
 },
 {
   "brand": "Afends",
   "avg_brand_rating": "4.0"
 },
 {
   "brand": "1 People",
   "avg_brand_rating": "4.0"
 },
 {
   "brand": "4Kinship",
   "avg_brand_rating": "4.0"
 },
 {
   "brand": "Adidas by Stella McCartney",
   "avg_brand_rating": "4.0"
 },
 {
   "brand": "ABLE",
   "avg_brand_rating": "4.0"
 },
 {
   "brand": "Aiayu",
   "avg_brand_rating": "4.0"
 },
 {
   "brand": "Alder",
   "avg_brand_rating": "3.0"
 },
 {
   "brand": "amaud",
   "avg_brand_rating": "5.0"
 },
 {
   "brand": "Amber Days",
   "avg_brand_rating": "4.0"
 },
 {
   "brand": "Aks",
   "avg_brand_rating": "4.0"
 },
 {
   "brand": "Ales Grey",
   "avg_brand_rating": "3.0"
 },
 {
   "brand": "ALMOST THERE",
   "avg_brand_rating": "4.0"
 },
 {
   "brand": "Akola",
   "avg_brand_rating": "4.0"
 },
 {
   "brand": "AKOIASWIM",
   "avg_brand_rating": "3.0"
 },
 {
   "brand": "Altar",
   "avg_brand_rating": "4.0"
 },
 {
   "brand": "Amber Goes Green",
   "avg_brand_rating": "4.0"
 },
 {
   "brand": "Allmade",
   "avg_brand_rating": "4.0"
 },
 {
   "brand": "Altra",
   "avg_brand_rating": "3.0"
 },
 {
   "brand": "Alighieri",
   "avg_brand_rating": "4.0"
 },
 {
   "brand": "Ana Luisa",
   "avg_brand_rating": "4.0"
 },
 {
   "brand": "Amble Outdoors",
   "avg_brand_rating": "4.0"
 },
 {
   "brand": "amt.",
   "avg_brand_rating": "4.0"
 },
 {
   "brand": "Alchemy Goods",
   "avg_brand_rating": "4.0"
 },
 {
   "brand": "Amour Vert",
   "avg_brand_rating": "4.0"
 },
 {
   "brand": "Akala",
   "avg_brand_rating": "4.0"
 },
 {
   "brand": "Alkemie",
   "avg_brand_rating": "4.0"
 },
 {
   "brand": "All Blues",
   "avg_brand_rating": "4.0"
 },
 {
   "brand": "ALEEM YUSUF",
   "avg_brand_rating": "4.0"
 },
 {
   "brand": "All The Wild Roses",
   "avg_brand_rating": "4.0"
 },
 {
   "brand": "Ambiletics",
   "avg_brand_rating": "4.0"
 },
 {
   "brand": "ALTER X Company",
   "avg_brand_rating": "4.0"
 },
 {
   "brand": "Amadeus",
   "avg_brand_rating": "4.0"
 },
 {
   "brand": "Alchemist",
   "avg_brand_rating": "4.0"
 },
 {
   "brand": "allthingsfi",
   "avg_brand_rating": "4.0"
 },
 {
   "brand": "ANTTI",
   "avg_brand_rating": "4.0"
 },
 {
   "brand": "Apple Oak Fibre Works",
   "avg_brand_rating": "5.0"
 },
 {
   "brand": "ANINI",
   "avg_brand_rating": "4.0"
 },
 {
   "brand": "Arc’teryx",
   "avg_brand_rating": "2.5"
 },
 {
   "brand": "Araks",
   "avg_brand_rating": "4.0"
 },
 {
   "brand": "Anne Hermine",
   "avg_brand_rating": "5.0"
 },
 {
   "brand": "Art’Abaska",
   "avg_brand_rating": "3.0"
 },
 {
   "brand": "Ansea",
   "avg_brand_rating": "4.0"
 },
 {
   "brand": "Artichoke",
   "avg_brand_rating": "4.0"
 },
 {
   "brand": "ARIELLE",
   "avg_brand_rating": "4.0"
 },
 {
   "brand": "Anthea Crawford",
   "avg_brand_rating": "4.0"
 },
 {
   "brand": "Antiform",
   "avg_brand_rating": "4.0"
 },
 {
   "brand": "AndAll",
   "avg_brand_rating": "4.0"
 },
 {
   "brand": "Arnsdorf",
   "avg_brand_rating": "4.0"
 },
 {
   "brand": "Anabela Chan",
   "avg_brand_rating": "4.0"
 },
 {
   "brand": "Andorine",
   "avg_brand_rating": "3.0"
 },
 {
   "brand": "Another Tomorrow",
   "avg_brand_rating": "4.0"
 },
 {
   "brand": "arch4",
   "avg_brand_rating": "3.0"
 },
 {
   "brand": "Arrels Barcelona",
   "avg_brand_rating": "4.0"
 },
 {
   "brand": "Annie Hamilton",
   "avg_brand_rating": "4.0"
 },
 {
   "brand": "Antonello Tedde",
   "avg_brand_rating": "4.0"
 },
 {
   "brand": "Anchal",
   "avg_brand_rating": "4.0"
 },
 {
   "brand": "ARTICLE22",
   "avg_brand_rating": "4.0"
 },
 {
   "brand": "Après Studio",
   "avg_brand_rating": "4.0"
 },
 {
   "brand": "Artknit Studios",
   "avg_brand_rating": "4.0"
 },
 {
   "brand": "Andersen-Andersen",
   "avg_brand_rating": "4.0"
 },
 {
   "brand": "Anekdot",
   "avg_brand_rating": "4.0"
 },
 {
   "brand": "Angels Ambition",
   "avg_brand_rating": "4.0"
 },
 {
   "brand": "Anywhere",
   "avg_brand_rating": "3.0"
 },
 {
   "brand": "Ay",
   "avg_brand_rating": "4.0"
 },
 {
   "brand": "AuTerra",
   "avg_brand_rating": "5.0"
 },
 {
   "brand": "B.L.A.H.",
   "avg_brand_rating": "3.0"
 },
 {
   "brand": "Aventura",
   "avg_brand_rating": "3.0"
 },
 {
   "brand": "BAGGU",
   "avg_brand_rating": "4.0"
 },
 {
   "brand": "Avila",
   "avg_brand_rating": "4.0"
 },
 {
   "brand": "Bandsome",
   "avg_brand_rating": "4.0"
 },
 {
   "brand": "Aware…the social design project",
   "avg_brand_rating": "4.0"
 },
 {
   "brand": "Aster & Oak",
   "avg_brand_rating": "5.0"
 },
 {
   "brand": "Automic Gold",
   "avg_brand_rating": "4.0"
 },
 {
   "brand": "autark",
   "avg_brand_rating": "4.0"
 },
 {
   "brand": "Ayten Gasson",
   "avg_brand_rating": "4.0"
 },
 {
   "brand": "BASTET NOIR",
   "avg_brand_rating": "4.0"
 },
 {
   "brand": "B_Boheme",
   "avg_brand_rating": "4.0"
 },
 {
   "brand": "Athleta",
   "avg_brand_rating": "3.0"
 },
 {
   "brand": "Avani",
   "avg_brand_rating": "4.0"
 },
 {
   "brand": "Atelier Lavoisier",
   "avg_brand_rating": "4.0"
 },
 {
   "brand": "Bario Neal",
   "avg_brand_rating": "4.0"
 },
 {
   "brand": "B Sides",
   "avg_brand_rating": "3.0"
 },
 {
   "brand": "AVNIER",
   "avg_brand_rating": "3.0"
 },
 {
   "brand": "Baserange",
   "avg_brand_rating": "4.0"
 },
 {
   "brand": "ASK SCANDINAVIA",
   "avg_brand_rating": "4.0"
 },
 {
   "brand": "Balenciaga",
   "avg_brand_rating": "3.0"
 },
 {
   "brand": "BALL",
   "avg_brand_rating": "3.0"
 },
 {
   "brand": "Bam Loves Boo",
   "avg_brand_rating": "4.0"
 },
 {
   "brand": "Band of Rascals",
   "avg_brand_rating": "5.0"
 },
 {
   "brand": "Baiia",
   "avg_brand_rating": "4.0"
 },
 {
   "brand": "Auria Paris",
   "avg_brand_rating": "5.0"
 },
 {
   "brand": "bleed",
   "avg_brand_rating": "4.0"
 },
 {
   "brand": "Bhumi",
   "avg_brand_rating": "4.0"
 },
 {
   "brand": "Bibico",
   "avg_brand_rating": "4.0"
 },
 {
   "brand": "BAYTHE",
   "avg_brand_rating": "4.0"
 },
 {
   "brand": "Beaumont Organic",
   "avg_brand_rating": "4.0"
 },
 {
   "brand": "Bellerose",
   "avg_brand_rating": "3.0"
 },
 {
   "brand": "Billi London",
   "avg_brand_rating": "4.0"
 },
 {
   "brand": "BEEN London",
   "avg_brand_rating": "4.0"
 },
 {
   "brand": "Blonde Gone Rogue",
   "avg_brand_rating": "4.0"
 },
 {
   "brand": "BeeKeeper Parade",
   "avg_brand_rating": "4.0"
 },
 {
   "brand": "Biehler",
   "avg_brand_rating": "4.0"
 },
 {
   "brand": "BEDI",
   "avg_brand_rating": "4.0"
 },
 {
   "brand": "Becci Boo’s Custom Shoes",
   "avg_brand_rating": "4.0"
 },
 {
   "brand": "BITE",
   "avg_brand_rating": "4.0"
 },
 {
   "brand": "Batoko",
   "avg_brand_rating": "4.0"
 },
 {
   "brand": "BeezyMama",
   "avg_brand_rating": "3.0"
 },
 {
   "brand": "Biankina",
   "avg_brand_rating": "4.0"
 },
 {
   "brand": "Blanche",
   "avg_brand_rating": "3.0"
 },
 {
   "brand": "Bianca Spender",
   "avg_brand_rating": "4.0"
 },
 {
   "brand": "Bleue Burnham",
   "avg_brand_rating": "4.0"
 },
 {
   "brand": "Batch 1 UK",
   "avg_brand_rating": "3.0"
 },
 {
   "brand": "Bethany Williams",
   "avg_brand_rating": "4.0"
 },
 {
   "brand": "Baukjen",
   "avg_brand_rating": "4.0"
 },
 {
   "brand": "behno",
   "avg_brand_rating": "4.0"
 },
 {
   "brand": "Better World Fashion",
   "avg_brand_rating": "4.0"
 },
 {
   "brand": "Beyond Skin",
   "avg_brand_rating": "4.0"
 },
 {
   "brand": "Beulah",
   "avg_brand_rating": "4.0"
 },
 {
   "brand": "Blue Of A Kind",
   "avg_brand_rating": "4.0"
 },
 {
   "brand": "Bilboa",
   "avg_brand_rating": "3.0"
 },
 {
   "brand": "Birdsong",
   "avg_brand_rating": "4.0"
 },
 {
   "brand": "Bozena Jankowska",
   "avg_brand_rating": "4.0"
 },
 {
   "brand": "BUFF",
   "avg_brand_rating": "4.0"
 },
 {
   "brand": "blufruit",
   "avg_brand_rating": "5.0"
 },
 {
   "brand": "bogdar",
   "avg_brand_rating": "4.0"
 },
 {
   "brand": "Brothers We Stand",
   "avg_brand_rating": "4.0"
 },
 {
   "brand": "BoBo GloBal",
   "avg_brand_rating": "4.0"
 },
 {
   "brand": "Bougainvillea London",
   "avg_brand_rating": "5.0"
 },
 {
   "brand": "BOTTLETOP",
   "avg_brand_rating": "4.0"
 },
 {
   "brand": "Bolso",
   "avg_brand_rating": "4.0"
 },
 {
   "brand": "Botto Giuseppe",
   "avg_brand_rating": "4.0"
 },
 {
   "brand": "Boob",
   "avg_brand_rating": "4.0"
 },
 {
   "brand": "Brava Fabrics",
   "avg_brand_rating": "4.0"
 },
 {
   "brand": "Boody",
   "avg_brand_rating": "4.0"
 },
 {
   "brand": "BRING",
   "avg_brand_rating": "4.0"
 },
 {
   "brand": "BONDI BORN",
   "avg_brand_rating": "4.0"
 },
 {
   "brand": "Blutsgeschwister",
   "avg_brand_rating": "4.0"
 },
 {
   "brand": "Bunti",
   "avg_brand_rating": "4.0"
 },
 {
   "brand": "Burgeon Outdoor",
   "avg_brand_rating": "3.0"
 },
 {
   "brand": "Bonito",
   "avg_brand_rating": "4.0"
 },
 {
   "brand": "Bow&Bo",
   "avg_brand_rating": "4.0"
 },
 {
   "brand": "Blue Wren Collective",
   "avg_brand_rating": "5.0"
 },
 {
   "brand": "Boucheron",
   "avg_brand_rating": "3.0"
 },
 {
   "brand": "Boll & Branch",
   "avg_brand_rating": "5.0"
 },
 {
   "brand": "Bobo Choses",
   "avg_brand_rating": "3.0"
 },
 {
   "brand": "Boma",
   "avg_brand_rating": "3.0"
 },
 {
   "brand": "BOA Basics",
   "avg_brand_rating": "4.0"
 },
 {
   "brand": "Bon Label",
   "avg_brand_rating": "4.5"
 },
 {
   "brand": "Bower",
   "avg_brand_rating": "4.0"
 },
 {
   "brand": "Bluebuck",
   "avg_brand_rating": "4.0"
 },
 {
   "brand": "Boyish",
   "avg_brand_rating": "4.0"
 },
 {
   "brand": "Chelsea Bravo",
   "avg_brand_rating": "4.0"
 },
 {
   "brand": "Charli Cohen",
   "avg_brand_rating": "4.0"
 },
 {
   "brand": "CARCEL",
   "avg_brand_rating": "3.0"
 },
 {
   "brand": "By Walid",
   "avg_brand_rating": "4.0"
 },
 {
   "brand": "Casa Raki",
   "avg_brand_rating": "4.0"
 },
 {
   "brand": "Chillax",
   "avg_brand_rating": "4.0"
 },
 {
   "brand": "BYBBA",
   "avg_brand_rating": "4.0"
 },
 {
   "brand": "Charlee Swim",
   "avg_brand_rating": "5.0"
 },
 {
   "brand": "Camp Cove Swim",
   "avg_brand_rating": "4.0"
 },
 {
   "brand": "Capodimonti Cashmere",
   "avg_brand_rating": "4.0"
 },
 {
   "brand": "Chick Lane",
   "avg_brand_rating": "3.0"
 },
 {
   "brand": "Cagey’s Planet",
   "avg_brand_rating": "4.0"
 },
 {
   "brand": "CAFIN",
   "avg_brand_rating": "4.0"
 },
 {
   "brand": "Burton",
   "avg_brand_rating": "3.0"
 },
 {
   "brand": "Calle Del Mar",
   "avg_brand_rating": "4.0"
 },
 {
   "brand": "CARPASUS",
   "avg_brand_rating": "4.0"
 },
 {
   "brand": "Chic Made Consciously",
   "avg_brand_rating": "4.0"
 },
 {
   "brand": "Casco Totes",
   "avg_brand_rating": "4.0"
 },
 {
   "brand": "CASUPO",
   "avg_brand_rating": "3.0"
 },
 {
   "brand": "Burnt Soul",
   "avg_brand_rating": "4.0"
 },
 {
   "brand": "CARIUMA",
   "avg_brand_rating": "4.0"
 },
 {
   "brand": "CARE BY ME",
   "avg_brand_rating": "4.0"
 },
 {
   "brand": "Caftanii",
   "avg_brand_rating": "3.0"
 },
 {
   "brand": "BUSHY",
   "avg_brand_rating": "4.0"
 },
 {
   "brand": "CasaGIN",
   "avg_brand_rating": "4.0"
 },
 {
   "brand": "Carlie Ballard",
   "avg_brand_rating": "4.5"
 },
 {
   "brand": "Charlie Mae Swimwear",
   "avg_brand_rating": "4.0"
 },
 {
   "brand": "Catarina Mina",
   "avg_brand_rating": "3.0"
 },
 {
   "brand": "Carmina Campus",
   "avg_brand_rating": "4.0"
 },
 {
   "brand": "CAES",
   "avg_brand_rating": "4.0"
 },
 {
   "brand": "Classic Cotton Co",
   "avg_brand_rating": "4.0"
 },
 {
   "brand": "Converse",
   "avg_brand_rating": "3.0"
 },
 {
   "brand": "Circle Sportswear",
   "avg_brand_rating": "3.0"
 },
 {
   "brand": "COG",
   "avg_brand_rating": "4.0"
 },
 {
   "brand": "CHPO",
   "avg_brand_rating": "3.0"
 },
 {
   "brand": "ColieCo",
   "avg_brand_rating": "4.5"
 },
 {
   "brand": "Club Chainstitch",
   "avg_brand_rating": "3.0"
 },
 {
   "brand": "Christy Dawn",
   "avg_brand_rating": "5.0"
 },
 {
   "brand": "Chopova Lowena",
   "avg_brand_rating": "4.0"
 },
 {
   "brand": "Citizen Wolf",
   "avg_brand_rating": "4.5"
 },
 {
   "brand": "Coco & Kandy",
   "avg_brand_rating": "4.0"
 },
 {
   "brand": "CLOUDY",
   "avg_brand_rating": "4.0"
 },
 {
   "brand": "Coolawoola",
   "avg_brand_rating": "4.0"
 },
 {
   "brand": "Colorado Threads",
   "avg_brand_rating": "3.0"
 },
 {
   "brand": "Cleobella",
   "avg_brand_rating": "4.0"
 },
 {
   "brand": "Corkor",
   "avg_brand_rating": "4.0"
 },
 {
   "brand": "Come Back As A Flower",
   "avg_brand_rating": "4.0"
 },
 {
   "brand": "Contessa Volpi",
   "avg_brand_rating": "4.0"
 },
 {
   "brand": "Ciganka – Artforms from Nature",
   "avg_brand_rating": "5.0"
 },
 {
   "brand": "Clubhouse Vintage",
   "avg_brand_rating": "4.0"
 },
 {
   "brand": "Conscious the label",
   "avg_brand_rating": "4.0"
 },
 {
   "brand": "COSSAC",
   "avg_brand_rating": "4.0"
 },
 {
   "brand": "Continew",
   "avg_brand_rating": "4.0"
 },
 {
   "brand": "Cingomma",
   "avg_brand_rating": "4.0"
 },
 {
   "brand": "Coq en Pâte",
   "avg_brand_rating": "4.0"
 },
 {
   "brand": "Circos",
   "avg_brand_rating": "4.0"
 },
 {
   "brand": "DAWN Denim",
   "avg_brand_rating": "5.0"
 },
 {
   "brand": "Coyuchi",
   "avg_brand_rating": "4.0"
 },
 {
   "brand": "Dai",
   "avg_brand_rating": "4.0"
 },
 {
   "brand": "Crystalyn Kae",
   "avg_brand_rating": "4.0"
 },
 {
   "brand": "Cus",
   "avg_brand_rating": "4.0"
 },
 {
   "brand": "Diemonde",
   "avg_brand_rating": "3.0"
 },
 {
   "brand": "Dharma Bums",
   "avg_brand_rating": "5.0"
 },
 {
   "brand": "Deadwood",
   "avg_brand_rating": "4.0"
 },
 {
   "brand": "Deux Mains",
   "avg_brand_rating": "4.0"
 },
 {
   "brand": "Cuisse de Grenouille",
   "avg_brand_rating": "3.0"
 },
 {
   "brand": "Day Won",
   "avg_brand_rating": "4.0"
 },
 {
   "brand": "Desert Dyes",
   "avg_brand_rating": "4.0"
 },
 {
   "brand": "Desmond & Dempsey",
   "avg_brand_rating": "4.0"
 },
 {
   "brand": "Dickies",
   "avg_brand_rating": "3.0"
 },
 {
   "brand": "Destination Dress",
   "avg_brand_rating": "4.0"
 },
 {
   "brand": "Dear Denier",
   "avg_brand_rating": "4.0"
 },
 {
   "brand": "D&DEPARTMENT",
   "avg_brand_rating": "4.0"
 },
 {
   "brand": "Delayne Dixon",
   "avg_brand_rating": "4.0"
 },
 {
   "brand": "Designers Remix",
   "avg_brand_rating": "4.0"
 },
 {
   "brand": "Dilli Grey",
   "avg_brand_rating": "4.0"
 },
 {
   "brand": "Cousin Billie",
   "avg_brand_rating": "4.0"
 },
 {
   "brand": "Dazey LA",
   "avg_brand_rating": "3.0"
 },
 {
   "brand": "Dear Darling Berlin",
   "avg_brand_rating": "4.0"
 },
 {
   "brand": "Dapper Alice",
   "avg_brand_rating": "4.0"
 },
 {
   "brand": "DAYWEARLAB",
   "avg_brand_rating": "4.0"
 },
 {
   "brand": "Delikate Rayne",
   "avg_brand_rating": "4.0"
 },
 {
   "brand": "éclipse",
   "avg_brand_rating": "5.0"
 },
 {
   "brand": "Ekta Helsinki",
   "avg_brand_rating": "4.0"
 },
 {
   "brand": "Earth Divas",
   "avg_brand_rating": "4.0"
 },
 {
   "brand": "Dimples",
   "avg_brand_rating": "4.0"
 },
 {
   "brand": "Dots On Tots",
   "avg_brand_rating": "4.0"
 },
 {
   "brand": "Edwin USA",
   "avg_brand_rating": "4.0"
 },
 {
   "brand": "Ecoology",
   "avg_brand_rating": "4.0"
 },
 {
   "brand": "Edeline Lee",
   "avg_brand_rating": "4.0"
 },
 {
   "brand": "Dirty Velvet",
   "avg_brand_rating": "4.0"
 },
 {
   "brand": "Ecologie by AWDis",
   "avg_brand_rating": "4.0"
 },
 {
   "brand": "Eco Intimates",
   "avg_brand_rating": "4.0"
 },
 {
   "brand": "Dora Larsen",
   "avg_brand_rating": "4.0"
 },
 {
   "brand": "Dorsu",
   "avg_brand_rating": "5.0"
 },
 {
   "brand": "EcoRight",
   "avg_brand_rating": "4.0"
 },
 {
   "brand": "Dreamers & Drifters",
   "avg_brand_rating": "3.0"
 },
 {
   "brand": "econscious",
   "avg_brand_rating": "4.0"
 },
 {
   "brand": "Donatella Fabio Beachwear",
   "avg_brand_rating": "3.0"
 },
 {
   "brand": "Dominique Healy",
   "avg_brand_rating": "4.0"
 },
 {
   "brand": "DuchXFashion",
   "avg_brand_rating": "5.0"
 },
 {
   "brand": "E.L.V. Denim",
   "avg_brand_rating": "5.0"
 },
 {
   "brand": "Dressarte Paris",
   "avg_brand_rating": "4.0"
 },
 {
   "brand": "Drivemebikini",
   "avg_brand_rating": "3.0"
 },
 {
   "brand": "Divine",
   "avg_brand_rating": "4.0"
 },
 {
   "brand": "dk active",
   "avg_brand_rating": "5.0"
 },
 {
   "brand": "Eileen Fisher",
   "avg_brand_rating": "4.0"
 },
 {
   "brand": "ecuvo",
   "avg_brand_rating": "4.0"
 },
 {
   "brand": "DÔEN",
   "avg_brand_rating": "3.0"
 },
 {
   "brand": "Eguzkilore",
   "avg_brand_rating": "4.0"
 },
 {
   "brand": "Dresden",
   "avg_brand_rating": "3.0"
 },
 {
   "brand": "émoi émoi",
   "avg_brand_rating": "3.0"
 },
 {
   "brand": "Endless Joy",
   "avg_brand_rating": "4.0"
 },
 {
   "brand": "ÉTICA",
   "avg_brand_rating": "5.0"
 },
 {
   "brand": "ETQ",
   "avg_brand_rating": "3.0"
 },
 {
   "brand": "Ethletic",
   "avg_brand_rating": "4.0"
 },
 {
   "brand": "Elkline",
   "avg_brand_rating": "4.0"
 },
 {
   "brand": "Fabrik",
   "avg_brand_rating": "4.0"
 },
 {
   "brand": "EllA Fashion",
   "avg_brand_rating": "4.0"
 },
 {
   "brand": "ENDANGERED",
   "avg_brand_rating": "4.0"
 },
 {
   "brand": "eleven44",
   "avg_brand_rating": "3.0"
 },
 {
   "brand": "Enfant Terrible",
   "avg_brand_rating": "4.0"
 },
 {
   "brand": "Erin Draper",
   "avg_brand_rating": "4.0"
 },
 {
   "brand": "Elk",
   "avg_brand_rating": "4.0"
 },
 {
   "brand": "Erba",
   "avg_brand_rating": "4.0"
 },
 {
   "brand": "Elsien Gringhuis",
   "avg_brand_rating": "4.0"
 },
 {
   "brand": "Enter the E",
   "avg_brand_rating": "4.0"
 },
 {
   "brand": "Elizabeth Suzann Studio",
   "avg_brand_rating": "4.0"
 },
 {
   "brand": "ettitude",
   "avg_brand_rating": "4.0"
 },
 {
   "brand": "Elliss",
   "avg_brand_rating": "4.0"
 },
 {
   "brand": "Elle Evans",
   "avg_brand_rating": "4.0"
 },
 {
   "brand": "Escama Studio",
   "avg_brand_rating": "4.0"
 },
 {
   "brand": "Engel",
   "avg_brand_rating": "4.0"
 },
 {
   "brand": "Encircled",
   "avg_brand_rating": "4.0"
 },
 {
   "brand": "Elvis & Kresse",
   "avg_brand_rating": "4.0"
 },
 {
   "brand": "El Naturalista",
   "avg_brand_rating": "3.0"
 },
 {
   "brand": "Ella & Witt",
   "avg_brand_rating": "4.0"
 },
 {
   "brand": "erlich textil",
   "avg_brand_rating": "3.0"
 },
 {
   "brand": "Elegantees",
   "avg_brand_rating": "4.0"
 },
 {
   "brand": "Everpress",
   "avg_brand_rating": "4.0"
 },
 {
   "brand": "Flamingos’ Life",
   "avg_brand_rating": "4.0"
 },
 {
   "brand": "Florence Given",
   "avg_brand_rating": "4.0"
 },
 {
   "brand": "Fresh Cuts Clothing",
   "avg_brand_rating": "4.0"
 },
 {
   "brand": "FM 669",
   "avg_brand_rating": "4.0"
 },
 {
   "brand": "Flare Street",
   "avg_brand_rating": "5.0"
 },
 {
   "brand": "Fair Harbor",
   "avg_brand_rating": "3.0"
 },
 {
   "brand": "FUTURA Jewelry",
   "avg_brand_rating": "5.0"
 },
 {
   "brand": "Floris van Bommel",
   "avg_brand_rating": "3.0"
 },
 {
   "brand": "Fayettechill",
   "avg_brand_rating": "4.0"
 },
 {
   "brand": "Free Label",
   "avg_brand_rating": "4.0"
 },
 {
   "brand": "FREED",
   "avg_brand_rating": "4.0"
 },
 {
   "brand": "Finn + Emma",
   "avg_brand_rating": "3.0"
 },
 {
   "brand": "FRANC",
   "avg_brand_rating": "4.0"
 },
 {
   "brand": "For Love and Lemons",
   "avg_brand_rating": "3.0"
 },
 {
   "brand": "Flax and Loom",
   "avg_brand_rating": "4.0"
 },
 {
   "brand": "Frugi",
   "avg_brand_rating": "4.0"
 },
 {
   "brand": "fairechild",
   "avg_brand_rating": "4.0"
 },
 {
   "brand": "Faithfull the Brand",
   "avg_brand_rating": "3.0"
 },
 {
   "brand": "Forét",
   "avg_brand_rating": "4.0"
 },
 {
   "brand": "FIL MELANGE",
   "avg_brand_rating": "4.0"
 },
 {
   "brand": "Fjällräven",
   "avg_brand_rating": "3.0"
 },
 {
   "brand": "Fair Indigo",
   "avg_brand_rating": "5.0"
 },
 {
   "brand": "FTC Cashmere",
   "avg_brand_rating": "4.0"
 },
 {
   "brand": "FTLA Apparel",
   "avg_brand_rating": "4.0"
 },
 {
   "brand": "Fanfare",
   "avg_brand_rating": "4.0"
 },
 {
   "brand": "FREITAG",
   "avg_brand_rating": "4.0"
 },
 {
   "brand": "Farm to Hanger",
   "avg_brand_rating": "4.0"
 },
 {
   "brand": "Flowfold",
   "avg_brand_rating": "3.0"
 },
 {
   "brand": "Galamaar",
   "avg_brand_rating": "3.0"
 },
 {
   "brand": "Gaia Segattini Knotwear",
   "avg_brand_rating": "4.0"
 },
 {
   "brand": "Good Guys",
   "avg_brand_rating": "4.0"
 },
 {
   "brand": "Gergana Ivanova",
   "avg_brand_rating": "3.0"
 },
 {
   "brand": "Good Citizens Eyewear",
   "avg_brand_rating": "4.0"
 },
 {
   "brand": "GAI+LISVA",
   "avg_brand_rating": "4.0"
 },
 {
   "brand": "Goddess Gear",
   "avg_brand_rating": "4.0"
 },
 {
   "brand": "Goat Organic Apparel",
   "avg_brand_rating": "4.0"
 },
 {
   "brand": "Glass Onion",
   "avg_brand_rating": "5.0"
 },
 {
   "brand": "Good for Sunday",
   "avg_brand_rating": "4.0"
 },
 {
   "brand": "Go Gently Nation",
   "avg_brand_rating": "4.0"
 },
 {
   "brand": "go as u.r",
   "avg_brand_rating": "4.0"
 },
 {
   "brand": "GR10K",
   "avg_brand_rating": "2.0"
 },
 {
   "brand": "GOT BAG",
   "avg_brand_rating": "3.0"
 },
 {
   "brand": "Granelito",
   "avg_brand_rating": "4.0"
 },
 {
   "brand": "goodtrip",
   "avg_brand_rating": "3.0"
 },
 {
   "brand": "Gina Marie Handbags",
   "avg_brand_rating": "4.0"
 },
 {
   "brand": "Gaia Conceptions",
   "avg_brand_rating": "4.0"
 },
 {
   "brand": "GARY MASH",
   "avg_brand_rating": "4.0"
 },
 {
   "brand": "Greenpacha",
   "avg_brand_rating": "3.0"
 },
 {
   "brand": "Garçon Français",
   "avg_brand_rating": "4.0"
 },
 {
   "brand": "Gazur",
   "avg_brand_rating": "4.0"
 },
 {
   "brand": "Graceful District",
   "avg_brand_rating": "4.0"
 },
 {
   "brand": "GOODEE",
   "avg_brand_rating": "4.0"
 },
 {
   "brand": "Gray Label",
   "avg_brand_rating": "4.0"
 },
 {
   "brand": "GRAMMAR",
   "avg_brand_rating": "4.0"
 },
 {
   "brand": "General Sleep",
   "avg_brand_rating": "4.0"
 },
 {
   "brand": "goodsociety",
   "avg_brand_rating": "4.0"
 },
 {
   "brand": "Greenfibres",
   "avg_brand_rating": "4.0"
 },
 {
   "brand": "HarperSage",
   "avg_brand_rating": "4.0"
 },
 {
   "brand": "HNST",
   "avg_brand_rating": "4.0"
 },
 {
   "brand": "GROUNDTRUTH",
   "avg_brand_rating": "4.0"
 },
 {
   "brand": "Hackwith Design House",
   "avg_brand_rating": "4.0"
 },
 {
   "brand": "Heiko",
   "avg_brand_rating": "4.0"
 },
 {
   "brand": "Hindbag",
   "avg_brand_rating": "4.0"
 },
 {
   "brand": "Happy Earth Apparel",
   "avg_brand_rating": "4.0"
 },
 {
   "brand": "HARA the label",
   "avg_brand_rating": "4.0"
 },
 {
   "brand": "harly jae",
   "avg_brand_rating": "4.0"
 },
 {
   "brand": "Haglöfs",
   "avg_brand_rating": "3.0"
 },
 {
   "brand": "Greg Lauren",
   "avg_brand_rating": "4.0"
 },
 {
   "brand": "GuterStoff",
   "avg_brand_rating": "4.0"
 },
 {
   "brand": "Hailey Gerrits",
   "avg_brand_rating": "4.0"
 },
 {
   "brand": "Gunda Hafner",
   "avg_brand_rating": "4.0"
 },
 {
   "brand": "Harriet Morris",
   "avg_brand_rating": "4.0"
 },
 {
   "brand": "Holly Ryan",
   "avg_brand_rating": "4.0"
 },
 {
   "brand": "Gugguu",
   "avg_brand_rating": "4.0"
 },
 {
   "brand": "HOCOSA",
   "avg_brand_rating": "3.0"
 },
 {
   "brand": "Hemen Biarritz",
   "avg_brand_rating": "4.0"
 },
 {
   "brand": "HERTH",
   "avg_brand_rating": "4.0"
 },
 {
   "brand": "Gung Ho Design",
   "avg_brand_rating": "4.0"
 },
 {
   "brand": "GUNAS",
   "avg_brand_rating": "4.0"
 },
 {
   "brand": "haikure",
   "avg_brand_rating": "3.0"
 },
 {
   "brand": "Grounded People",
   "avg_brand_rating": "4.0"
 },
 {
   "brand": "Harvest & Mill",
   "avg_brand_rating": "5.0"
 },
 {
   "brand": "Herdentier",
   "avg_brand_rating": "4.0"
 },
 {
   "brand": "Grüne Erde",
   "avg_brand_rating": "4.0"
 },
 {
   "brand": "Gyre",
   "avg_brand_rating": "4.0"
 },
 {
   "brand": "J. Hannah",
   "avg_brand_rating": "4.0"
 },
 {
   "brand": "Honest Basics",
   "avg_brand_rating": "4.0"
 },
 {
   "brand": "I was a Sari",
   "avg_brand_rating": "4.0"
 },
 {
   "brand": "HYER GOODS",
   "avg_brand_rating": "4.0"
 },
 {
   "brand": "Infantium Victoria",
   "avg_brand_rating": "4.5"
 },
 {
   "brand": "Hoppidi Handmade",
   "avg_brand_rating": "4.0"
 },
 {
   "brand": "Jack Wolfskin",
   "avg_brand_rating": "3.0"
 },
 {
   "brand": "Houdini",
   "avg_brand_rating": "4.0"
 },
 {
   "brand": "I’mdividual",
   "avg_brand_rating": "4.0"
 },
 {
   "brand": "Indego Africa",
   "avg_brand_rating": "4.0"
 },
 {
   "brand": "Hopaal",
   "avg_brand_rating": "5.0"
 },
 {
   "brand": "Isla In Bloom",
   "avg_brand_rating": "4.0"
 },
 {
   "brand": "INGMARSON",
   "avg_brand_rating": "4.0"
 },
 {
   "brand": "Icebug",
   "avg_brand_rating": "4.0"
 },
 {
   "brand": "HoMie",
   "avg_brand_rating": "3.0"
 },
 {
   "brand": "Ilk + Ernie",
   "avg_brand_rating": "4.0"
 },
 {
   "brand": "ID.EIGHT",
   "avg_brand_rating": "4.0"
 },
 {
   "brand": "ilovemixtapes",
   "avg_brand_rating": "4.0"
 },
 {
   "brand": "Hopeless Lingerie",
   "avg_brand_rating": "4.0"
 },
 {
   "brand": "iQ UV",
   "avg_brand_rating": "4.0"
 },
 {
   "brand": "INTOA design",
   "avg_brand_rating": "5.0"
 },
 {
   "brand": "Jackalo",
   "avg_brand_rating": "5.0"
 },
 {
   "brand": "Indiebride",
   "avg_brand_rating": "4.0"
 },
 {
   "brand": "In2Green",
   "avg_brand_rating": "4.0"
 },
 {
   "brand": "In The Soulshine",
   "avg_brand_rating": "4.0"
 },
 {
   "brand": "Horizon Athletic",
   "avg_brand_rating": "3.0"
 },
 {
   "brand": "JammaCaps",
   "avg_brand_rating": "3.0"
 },
 {
   "brand": "Johnstons of Elgin",
   "avg_brand_rating": "4.0"
 },
 {
   "brand": "Katla",
   "avg_brand_rating": "4.0"
 },
 {
   "brand": "JOYN",
   "avg_brand_rating": "4.0"
 },
 {
   "brand": "Jaffic",
   "avg_brand_rating": "3.0"
 },
 {
   "brand": "Kampos",
   "avg_brand_rating": "4.0"
 },
 {
   "brand": "Jyoti – Fair Works",
   "avg_brand_rating": "4.0"
 },
 {
   "brand": "JEM",
   "avg_brand_rating": "4.0"
 },
 {
   "brand": "Jamido",
   "avg_brand_rating": "4.0"
 },
 {
   "brand": "JENNIFER BEHR",
   "avg_brand_rating": "3.0"
 },
 {
   "brand": "Jackfruit the label",
   "avg_brand_rating": "5.0"
 },
 {
   "brand": "KAY KONECNA STUDIO",
   "avg_brand_rating": "4.0"
 },
 {
   "brand": "KATTAN",
   "avg_brand_rating": "4.0"
 },
 {
   "brand": "KasuReKids",
   "avg_brand_rating": "4.0"
 },
 {
   "brand": "Jamie + The Jones",
   "avg_brand_rating": "4.0"
 },
 {
   "brand": "JAN ‘N JUNE",
   "avg_brand_rating": "4.0"
 },
 {
   "brand": "Junk Studios",
   "avg_brand_rating": "4.0"
 },
 {
   "brand": "KAPOK KNOT",
   "avg_brand_rating": "4.0"
 },
 {
   "brand": "Joanie",
   "avg_brand_rating": "4.0"
 },
 {
   "brand": "Joslin",
   "avg_brand_rating": "4.0"
 },
 {
   "brand": "Joyya",
   "avg_brand_rating": "5.0"
 },
 {
   "brand": "Jenny Yoo",
   "avg_brand_rating": "3.0"
 },
 {
   "brand": "Katharine Hamnett",
   "avg_brand_rating": "4.0"
 },
 {
   "brand": "Juwelier Willer",
   "avg_brand_rating": "3.0"
 },
 {
   "brand": "Jillian Boustred",
   "avg_brand_rating": "3.0"
 },
 {
   "brand": "Josette la Chouette",
   "avg_brand_rating": "5.0"
 },
 {
   "brand": "Kapten & Son",
   "avg_brand_rating": "4.0"
 },
 {
   "brand": "Just Bee Queen",
   "avg_brand_rating": "3.0"
 },
 {
   "brand": "Kalaurie",
   "avg_brand_rating": "5.0"
 },
 {
   "brand": "Jungle Folk",
   "avg_brand_rating": "4.0"
 },
 {
   "brand": "Knock Knock",
   "avg_brand_rating": "4.0"
 },
 {
   "brand": "KIDSOFBROKENFUTURE",
   "avg_brand_rating": "4.0"
 },
 {
   "brand": "Kimoa",
   "avg_brand_rating": "3.0"
 },
 {
   "brand": "Kilomet109",
   "avg_brand_rating": "4.0"
 },
 {
   "brand": "Kings of Indigo",
   "avg_brand_rating": "4.5"
 },
 {
   "brand": "Konges Sløjd",
   "avg_brand_rating": "3.0"
 },
 {
   "brand": "Komodo",
   "avg_brand_rating": "4.0"
 },
 {
   "brand": "KENT",
   "avg_brand_rating": "4.0"
 },
 {
   "brand": "KORALI",
   "avg_brand_rating": "3.0"
 },
 {
   "brand": "KOHR",
   "avg_brand_rating": "5.0"
 },
 {
   "brand": "Kozii Swimwear",
   "avg_brand_rating": "3.0"
 },
 {
   "brand": "KnowledgeCotton Apparel",
   "avg_brand_rating": "4.0"
 },
 {
   "brand": "KIDS WORLDWIDE",
   "avg_brand_rating": "4.0"
 },
 {
   "brand": "Kuyichi",
   "avg_brand_rating": "4.0"
 },
 {
   "brand": "Krochet Kids",
   "avg_brand_rating": "4.0"
 },
 {
   "brand": "Kitikate",
   "avg_brand_rating": "4.0"
 },
 {
   "brand": "KIZASI",
   "avg_brand_rating": "4.0"
 },
 {
   "brand": "Kuwaii",
   "avg_brand_rating": "4.0"
 },
 {
   "brand": "KOKOworld",
   "avg_brand_rating": "4.0"
 },
 {
   "brand": "kekai Swimwear",
   "avg_brand_rating": "4.0"
 },
 {
   "brand": "Kiku Boutique",
   "avg_brand_rating": "4.0"
 },
 {
   "brand": "Klättermusen",
   "avg_brand_rating": "3.0"
 },
 {
   "brand": "Knickey",
   "avg_brand_rating": "5.0"
 },
 {
   "brand": "Know The Origin",
   "avg_brand_rating": "4.0"
 },
 {
   "brand": "Kordal Studio",
   "avg_brand_rating": "4.0"
 },
 {
   "brand": "Kimai",
   "avg_brand_rating": "4.0"
 },
 {
   "brand": "Leanne Marshall",
   "avg_brand_rating": "3.0"
 },
 {
   "brand": "LAmade Clothing",
   "avg_brand_rating": "3.0"
 },
 {
   "brand": "Lâcher Prise",
   "avg_brand_rating": "4.0"
 },
 {
   "brand": "LaBante",
   "avg_brand_rating": "4.0"
 },
 {
   "brand": "lemlem",
   "avg_brand_rating": "4.0"
 },
 {
   "brand": "Labienhecha",
   "avg_brand_rating": "4.0"
 },
 {
   "brand": "la fille d’O",
   "avg_brand_rating": "4.0"
 },
 {
   "brand": "Laura Lombardi",
   "avg_brand_rating": "4.0"
 },
 {
   "brand": "L’Estrange London",
   "avg_brand_rating": "4.0"
 },
 {
   "brand": "L’Envers",
   "avg_brand_rating": "4.0"
 },
 {
   "brand": "Lefrik",
   "avg_brand_rating": "4.0"
 },
 {
   "brand": "LAUDAE",
   "avg_brand_rating": "4.0"
 },
 {
   "brand": "LA Relaxed",
   "avg_brand_rating": "5.0"
 },
 {
   "brand": "LDP",
   "avg_brand_rating": "5.0"
 },
 {
   "brand": "Lauren Holloway",
   "avg_brand_rating": "4.0"
 },
 {
   "brand": "La Methode",
   "avg_brand_rating": "4.0"
 },
 {
   "brand": "Laura Elizabeth Jewelry",
   "avg_brand_rating": "4.0"
 },
 {
   "brand": "Lapuan Kankurit",
   "avg_brand_rating": "4.0"
 },
 {
   "brand": "Kysal",
   "avg_brand_rating": "4.0"
 },
 {
   "brand": "Lando Studio",
   "avg_brand_rating": "4.0"
 },
 {
   "brand": "lana",
   "avg_brand_rating": "4.0"
 },
 {
   "brand": "Leisure Lab",
   "avg_brand_rating": "3.0"
 },
 {
   "brand": "Leni Swims",
   "avg_brand_rating": "4.0"
 },
 {
   "brand": "LangerChen",
   "avg_brand_rating": "4.0"
 },
 {
   "brand": "LANIUS",
   "avg_brand_rating": "4.0"
 },
 {
   "brand": "Kzeniya",
   "avg_brand_rating": "4.0"
 },
 {
   "brand": "les boutons",
   "avg_brand_rating": "4.0"
 },
 {
   "brand": "La Bottega di Brunella",
   "avg_brand_rating": "3.0"
 },
 {
   "brand": "Lazy Oaf",
   "avg_brand_rating": "3.0"
 },
 {
   "brand": "Le Loopas",
   "avg_brand_rating": "4.0"
 },
 {
   "brand": "Linenfox",
   "avg_brand_rating": "4.0"
 },
 {
   "brand": "Licia Florio",
   "avg_brand_rating": "4.0"
 },
 {
   "brand": "Losano",
   "avg_brand_rating": "4.0"
 },
 {
   "brand": "Lost in Paris",
   "avg_brand_rating": "5.0"
 },
 {
   "brand": "Libeco",
   "avg_brand_rating": "4.0"
 },
 {
   "brand": "Little Emperor",
   "avg_brand_rating": "4.0"
 },
 {
   "brand": "Linen Wedding Dress",
   "avg_brand_rating": "3.0"
 },
 {
   "brand": "Lionel the Label",
   "avg_brand_rating": "4.0"
 },
 {
   "brand": "Les Récupérables",
   "avg_brand_rating": "4.0"
 },
 {
   "brand": "Little Man Happy",
   "avg_brand_rating": "4.0"
 },
 {
   "brand": "Londre Bodywear",
   "avg_brand_rating": "4.0"
 },
 {
   "brand": "Lola & Stella",
   "avg_brand_rating": "4.0"
 },
 {
   "brand": "Liv:ra",
   "avg_brand_rating": "4.0"
 },
 {
   "brand": "Living Crafts",
   "avg_brand_rating": "5.0"
 },
 {
   "brand": "LONGEVITY LONDON",
   "avg_brand_rating": "4.0"
 },
 {
   "brand": "Löffler",
   "avg_brand_rating": "3.0"
 },
 {
   "brand": "loud + proud",
   "avg_brand_rating": "5.0"
 },
 {
   "brand": "London W11",
   "avg_brand_rating": "4.0"
 },
 {
   "brand": "Little Green Radicals",
   "avg_brand_rating": "5.0"
 },
 {
   "brand": "LNDR",
   "avg_brand_rating": "3.0"
 },
 {
   "brand": "Lilian von Trapp",
   "avg_brand_rating": "5.0"
 },
 {
   "brand": "Little Nature Lover",
   "avg_brand_rating": "4.0"
 },
 {
   "brand": "Looptworks",
   "avg_brand_rating": "4.0"
 },
 {
   "brand": "Lilac Limited Crochet",
   "avg_brand_rating": "3.0"
 },
 {
   "brand": "Linenbee",
   "avg_brand_rating": "4.0"
 },
 {
   "brand": "Lonely Kids Club",
   "avg_brand_rating": "4.0"
 },
 {
   "brand": "Loop Swim",
   "avg_brand_rating": "4.0"
 },
 {
   "brand": "LOCI",
   "avg_brand_rating": "4.0"
 },
 {
   "brand": "Lezat",
   "avg_brand_rating": "4.0"
 },
 {
   "brand": "LOCAL EUROPEAN",
   "avg_brand_rating": "2.0"
 },
 {
   "brand": "Magenta Threads",
   "avg_brand_rating": "4.0"
 },
 {
   "brand": "Louisa Parris",
   "avg_brand_rating": "4.0"
 },
 {
   "brand": "Love and Confuse",
   "avg_brand_rating": "2.0"
 },
 {
   "brand": "Madia & Matilda",
   "avg_brand_rating": "4.0"
 },
 {
   "brand": "MANDALA",
   "avg_brand_rating": "4.0"
 },
 {
   "brand": "LUNGE",
   "avg_brand_rating": "4.0"
 },
 {
   "brand": "LOUDBODIES",
   "avg_brand_rating": "4.0"
 },
 {
   "brand": "LOVJOI",
   "avg_brand_rating": "4.0"
 },
 {
   "brand": "Mara Hoffman",
   "avg_brand_rating": "4.0"
 },
 {
   "brand": "Make An Impact",
   "avg_brand_rating": "4.0"
 },
 {
   "brand": "LoveLux",
   "avg_brand_rating": "4.0"
 },
 {
   "brand": "Maggie Marilyn",
   "avg_brand_rating": "4.0"
 },
 {
   "brand": "Mario Doni",
   "avg_brand_rating": "3.0"
 },
 {
   "brand": "LUNA & ROSE",
   "avg_brand_rating": "4.0"
 },
 {
   "brand": "Luva Huva",
   "avg_brand_rating": "4.0"
 },
 {
   "brand": "Magpie Goose",
   "avg_brand_rating": "4.0"
 },
 {
   "brand": "Lusana",
   "avg_brand_rating": "3.0"
 },
 {
   "brand": "Mama;licious",
   "avg_brand_rating": "3.0"
 },
 {
   "brand": "LOVE BRAND & Co",
   "avg_brand_rating": "4.0"
 },
 {
   "brand": "Luxtra",
   "avg_brand_rating": "4.0"
 },
 {
   "brand": "Mantis World",
   "avg_brand_rating": "5.0"
 },
 {
   "brand": "Marks & Spencer",
   "avg_brand_rating": "3.0"
 },
 {
   "brand": "Luna + Sun",
   "avg_brand_rating": "4.0"
 },
 {
   "brand": "Mariclaro",
   "avg_brand_rating": "5.0"
 },
 {
   "brand": "Manimekala",
   "avg_brand_rating": "4.0"
 },
 {
   "brand": "MagicLinen",
   "avg_brand_rating": "3.0"
 },
 {
   "brand": "Loyal E. Paris",
   "avg_brand_rating": "4.0"
 },
 {
   "brand": "Marcia",
   "avg_brand_rating": "4.0"
 },
 {
   "brand": "Malaika New York",
   "avg_brand_rating": "4.0"
 },
 {
   "brand": "MIMIKRI",
   "avg_brand_rating": "4.0"
 },
 {
   "brand": "Maxomorra",
   "avg_brand_rating": "4.0"
 },
 {
   "brand": "MIAOU",
   "avg_brand_rating": "4.0"
 },
 {
   "brand": "Merry People",
   "avg_brand_rating": "3.0"
 },
 {
   "brand": "Mila.Vert",
   "avg_brand_rating": "5.0"
 },
 {
   "brand": "Melissa Joy Manning",
   "avg_brand_rating": "5.0"
 },
 {
   "brand": "Megan Leone Designs",
   "avg_brand_rating": "4.0"
 },
 {
   "brand": "Mashu",
   "avg_brand_rating": "4.0"
 },
 {
   "brand": "MiiK",
   "avg_brand_rating": "4.0"
 },
 {
   "brand": "Miga Swimwear",
   "avg_brand_rating": "4.0"
 },
 {
   "brand": "Meemoza",
   "avg_brand_rating": "4.0"
 },
 {
   "brand": "MATONA",
   "avg_brand_rating": "4.0"
 },
 {
   "brand": "Miakoda",
   "avg_brand_rating": "4.0"
 },
 {
   "brand": "Martina Spetlova",
   "avg_brand_rating": "4.0"
 },
 {
   "brand": "milo+nicki",
   "avg_brand_rating": "4.0"
 },
 {
   "brand": "Mien",
   "avg_brand_rating": "4.0"
 },
 {
   "brand": "Mighty Good Basics",
   "avg_brand_rating": "5.0"
 },
 {
   "brand": "Mayamiko",
   "avg_brand_rating": "5.0"
 },
 {
   "brand": "Marlies Dekkers",
   "avg_brand_rating": "3.0"
 },
 {
   "brand": "Mightly",
   "avg_brand_rating": "4.0"
 },
 {
   "brand": "Mars Loves Her",
   "avg_brand_rating": "4.0"
 },
 {
   "brand": "Materiel",
   "avg_brand_rating": "4.0"
 },
 {
   "brand": "Martha Medeiros",
   "avg_brand_rating": "2.0"
 },
 {
   "brand": "MELAWEAR",
   "avg_brand_rating": "4.0"
 },
 {
   "brand": "Milkweed Baby",
   "avg_brand_rating": "3.0"
 },
 {
   "brand": "Maya Magal",
   "avg_brand_rating": "4.0"
 },
 {
   "brand": "Mata Traders",
   "avg_brand_rating": "4.0"
 },
 {
   "brand": "Mimi Holvast",
   "avg_brand_rating": "4.0"
 },
 {
   "brand": "Mimi Prober",
   "avg_brand_rating": "4.0"
 },
 {
   "brand": "Miss Rose Sister Violet",
   "avg_brand_rating": "3.0"
 },
 {
   "brand": "Molo",
   "avg_brand_rating": "4.0"
 },
 {
   "brand": "Mirasa Design",
   "avg_brand_rating": "4.0"
 },
 {
   "brand": "Most Prominent Co.",
   "avg_brand_rating": "4.0"
 },
 {
   "brand": "MINI A TURE",
   "avg_brand_rating": "3.0"
 },
 {
   "brand": "Monkee Genes",
   "avg_brand_rating": "4.0"
 },
 {
   "brand": "Mnmur",
   "avg_brand_rating": "5.0"
 },
 {
   "brand": "Minimalist",
   "avg_brand_rating": "4.0"
 },
 {
   "brand": "Morgan Lane",
   "avg_brand_rating": "4.0"
 },
 {
   "brand": "Muchachomalo",
   "avg_brand_rating": "3.0"
 },
 {
   "brand": "mmb by hand",
   "avg_brand_rating": "4.0"
 },
 {
   "brand": "Modibodi",
   "avg_brand_rating": "3.5"
 },
 {
   "brand": "Mini Rodini",
   "avg_brand_rating": "4.0"
 },
 {
   "brand": "MIUSA",
   "avg_brand_rating": "4.0"
 },
 {
   "brand": "Modallica",
   "avg_brand_rating": "4.0"
 },
 {
   "brand": "Mworks",
   "avg_brand_rating": "4.0"
 },
 {
   "brand": "MinimalisticLinen",
   "avg_brand_rating": "4.0"
 },
 {
   "brand": "MONKIND",
   "avg_brand_rating": "4.0"
 },
 {
   "brand": "Monica Vinader",
   "avg_brand_rating": "4.0"
 },
 {
   "brand": "Mumutane",
   "avg_brand_rating": "4.0"
 },
 {
   "brand": "mori",
   "avg_brand_rating": "4.0"
 },
 {
   "brand": "MISSING",
   "avg_brand_rating": "4.0"
 },
 {
   "brand": "Mother of Pearl",
   "avg_brand_rating": "4.0"
 },
 {
   "brand": "Moumout",
   "avg_brand_rating": "3.0"
 },
 {
   "brand": "Monsoon Blooms",
   "avg_brand_rating": "5.0"
 },
 {
   "brand": "Mochi",
   "avg_brand_rating": "4.0"
 },
 {
   "brand": "Mireia Playà",
   "avg_brand_rating": "4.0"
 },
 {
   "brand": "Monica + Andy",
   "avg_brand_rating": "3.0"
 },
 {
   "brand": "Nat-2",
   "avg_brand_rating": "4.0"
 },
 {
   "brand": "Nightswim",
   "avg_brand_rating": "5.0"
 },
 {
   "brand": "Näz",
   "avg_brand_rating": "4.0"
 },
 {
   "brand": "NDX",
   "avg_brand_rating": "4.0"
 },
 {
   "brand": "Natalie Perry",
   "avg_brand_rating": "4.0"
 },
 {
   "brand": "Naja",
   "avg_brand_rating": "4.0"
 },
 {
   "brand": "NICO",
   "avg_brand_rating": "4.0"
 },
 {
   "brand": "Natalija",
   "avg_brand_rating": "4.0"
 },
 {
   "brand": "NIKIN",
   "avg_brand_rating": "4.0"
 },
 {
   "brand": "Nimble",
   "avg_brand_rating": "3.0"
 },
 {
   "brand": "NiciArt",
   "avg_brand_rating": "3.0"
 },
 {
   "brand": "NAGNATA",
   "avg_brand_rating": "4.0"
 },
 {
   "brand": "NAGO",
   "avg_brand_rating": "4.0"
 },
 {
   "brand": "Napapijri",
   "avg_brand_rating": "3.0"
 },
 {
   "brand": "Natasha Tonic",
   "avg_brand_rating": "4.0"
 },
 {
   "brand": "MYMARINI",
   "avg_brand_rating": "4.0"
 },
 {
   "brand": "Natalie Marie Jewellery",
   "avg_brand_rating": "4.0"
 },
 {
   "brand": "NAE Vegan Shoes",
   "avg_brand_rating": "4.0"
 },
 {
   "brand": "Neococo",
   "avg_brand_rating": "4.0"
 },
 {
   "brand": "Myrrhia Fine Knitwear",
   "avg_brand_rating": "4.0"
 },
 {
   "brand": "Neem",
   "avg_brand_rating": "4.0"
 },
 {
   "brand": "nat’v basics",
   "avg_brand_rating": "4.0"
 },
 {
   "brand": "Natalie Rolt",
   "avg_brand_rating": "4.0"
 },
 {
   "brand": "Nike",
   "avg_brand_rating": "3.0"
 },
 {
   "brand": "Nina Nest",
   "avg_brand_rating": "4.0"
 },
 {
   "brand": "Natascha von Hirschhausen",
   "avg_brand_rating": "4.0"
 },
 {
   "brand": "Mykke Hoffmann",
   "avg_brand_rating": "4.0"
 },
 {
   "brand": "Nena & Co.",
   "avg_brand_rating": "3.0"
 },
 {
   "brand": "Neu Nomads",
   "avg_brand_rating": "5.0"
 },
 {
   "brand": "Nina Rein",
   "avg_brand_rating": "4.0"
 },
 {
   "brand": "Noani",
   "avg_brand_rating": "4.0"
 },
 {
   "brand": "Noctu",
   "avg_brand_rating": "4.5"
 },
 {
   "brand": "Nui Organics",
   "avg_brand_rating": "4.0"
 },
 {
   "brand": "Nomadic State of Mind",
   "avg_brand_rating": "4.0"
 },
 {
   "brand": "O My Bag",
   "avg_brand_rating": "4.0"
 },
 {
   "brand": "nu-in",
   "avg_brand_rating": "4.0"
 },
 {
   "brand": "Nobody Denim",
   "avg_brand_rating": "4.0"
 },
 {
   "brand": "Niovi Organics",
   "avg_brand_rating": "4.0"
 },
 {
   "brand": "NoMiNoU",
   "avg_brand_rating": "4.0"
 },
 {
   "brand": "Nu Swim",
   "avg_brand_rating": "4.0"
 },
 {
   "brand": "Norden",
   "avg_brand_rating": "4.0"
 },
 {
   "brand": "Noumenon",
   "avg_brand_rating": "4.0"
 },
 {
   "brand": "Nothing New",
   "avg_brand_rating": "4.0"
 },
 {
   "brand": "Normal Knit",
   "avg_brand_rating": "4.0"
 },
 {
   "brand": "NOT OURS",
   "avg_brand_rating": "3.0"
 },
 {
   "brand": "Nisa",
   "avg_brand_rating": "4.5"
 },
 {
   "brand": "NINA YUUN",
   "avg_brand_rating": "4.0"
 },
 {
   "brand": "nobodinoz",
   "avg_brand_rating": "3.0"
 },
 {
   "brand": "Non",
   "avg_brand_rating": "4.5"
 },
 {
   "brand": "Nurture The Nest",
   "avg_brand_rating": "3.0"
 },
 {
   "brand": "Nomads Clothing",
   "avg_brand_rating": "4.0"
 },
 {
   "brand": "Nube",
   "avg_brand_rating": "5.0"
 },
 {
   "brand": "NOAH",
   "avg_brand_rating": "4.0"
 },
 {
   "brand": "Not Just Pajama",
   "avg_brand_rating": "4.0"
 },
 {
   "brand": "Nubikk",
   "avg_brand_rating": "3.0"
 },
 {
   "brand": "Ognx",
   "avg_brand_rating": "3.5"
 },
 {
   "brand": "Olmsted Outerwear",
   "avg_brand_rating": "4.5"
 },
 {
   "brand": "Oobi",
   "avg_brand_rating": "3.0"
 },
 {
   "brand": "Ōshadi",
   "avg_brand_rating": "4.0"
 },
 {
   "brand": "OffOn",
   "avg_brand_rating": "4.0"
 },
 {
   "brand": "Orbasics",
   "avg_brand_rating": "5.0"
 },
 {
   "brand": "Origin",
   "avg_brand_rating": "4.0"
 },
 {
   "brand": "Oy",
   "avg_brand_rating": "4.0"
 },
 {
   "brand": "One Vintage",
   "avg_brand_rating": "4.0"
 },
 {
   "brand": "OVS",
   "avg_brand_rating": "3.0"
 },
 {
   "brand": "Olistic the Label",
   "avg_brand_rating": "4.0"
 },
 {
   "brand": "Organic Crew",
   "avg_brand_rating": "4.0"
 },
 {
   "brand": "Organique",
   "avg_brand_rating": "4.0"
 },
 {
   "brand": "Olderbrother",
   "avg_brand_rating": "3.0"
 },
 {
   "brand": "Okabashi",
   "avg_brand_rating": "4.0"
 },
 {
   "brand": "Orit Elhanati",
   "avg_brand_rating": "4.0"
 },
 {
   "brand": "Original Weekend",
   "avg_brand_rating": "4.0"
 },
 {
   "brand": "OMNES",
   "avg_brand_rating": "4.0"
 },
 {
   "brand": "Otiumberg",
   "avg_brand_rating": "4.0"
 },
 {
   "brand": "Offbeat Sweetie",
   "avg_brand_rating": "4.0"
 },
 {
   "brand": "Oddish",
   "avg_brand_rating": "4.0"
 },
 {
   "brand": "OhSevenDays",
   "avg_brand_rating": "4.0"
 },
 {
   "brand": "Ohoy Swim",
   "avg_brand_rating": "3.0"
 },
 {
   "brand": "O.T.A",
   "avg_brand_rating": "4.0"
 },
 {
   "brand": "Opera Campi",
   "avg_brand_rating": "4.0"
 },
 {
   "brand": "Osei-Duro",
   "avg_brand_rating": "4.0"
 },
 {
   "brand": "Olga Joan",
   "avg_brand_rating": "4.0"
 },
 {
   "brand": "Paparesta Accessories",
   "avg_brand_rating": "4.0"
 },
 {
   "brand": "Patrick McDowell",
   "avg_brand_rating": "4.0"
 },
 {
   "brand": "Pecegueiro & F.os",
   "avg_brand_rating": "3.0"
 },
 {
   "brand": "Phoebe English",
   "avg_brand_rating": "4.0"
 },
 {
   "brand": "Par Moi",
   "avg_brand_rating": "4.0"
 },
 {
   "brand": "Parva Studios",
   "avg_brand_rating": "4.0"
 },
 {
   "brand": "Petits Vilains",
   "avg_brand_rating": "4.0"
 },
 {
   "brand": "peony",
   "avg_brand_rating": "4.0"
 },
 {
   "brand": "Passion Lilie",
   "avg_brand_rating": "4.5"
 },
 {
   "brand": "Petit Pli",
   "avg_brand_rating": "4.0"
 },
 {
   "brand": "Parade",
   "avg_brand_rating": "4.0"
 },
 {
   "brand": "Panamuna Project",
   "avg_brand_rating": "5.0"
 },
 {
   "brand": "PaaPii Design",
   "avg_brand_rating": "5.0"
 },
 {
   "brand": "Park & Fifth Clothing Co",
   "avg_brand_rating": "4.0"
 },
 {
   "brand": "PETERSON STOOP",
   "avg_brand_rating": "4.0"
 },
 {
   "brand": "Peninsula Swimwear",
   "avg_brand_rating": "3.0"
 },
 {
   "brand": "Palava",
   "avg_brand_rating": "4.0"
 },
 {
   "brand": "Phyne",
   "avg_brand_rating": "5.0"
 },
 {
   "brand": "Philine of San Francisco",
   "avg_brand_rating": "3.0"
 },
 {
   "brand": "Pareto",
   "avg_brand_rating": "4.0"
 },
 {
   "brand": "PH5",
   "avg_brand_rating": "3.0"
 },
 {
   "brand": "Pala Eyewear",
   "avg_brand_rating": "4.0"
 },
 {
   "brand": "Pansy",
   "avg_brand_rating": "4.0"
 },
 {
   "brand": "Pantee",
   "avg_brand_rating": "4.0"
 },
 {
   "brand": "Pop My Way",
   "avg_brand_rating": "4.0"
 },
 {
   "brand": "Plant Faced Clothing",
   "avg_brand_rating": "4.0"
 },
 {
   "brand": "Pure Magnolia",
   "avg_brand_rating": "4.0"
 },
 {
   "brand": "Proclaim",
   "avg_brand_rating": "5.0"
 },
 {
   "brand": "Piccalilly",
   "avg_brand_rating": "4.0"
 },
 {
   "brand": "Pressio",
   "avg_brand_rating": "4.0"
 },
 {
   "brand": "Prairie Underground",
   "avg_brand_rating": "4.0"
 },
 {
   "brand": "Pig and Hen",
   "avg_brand_rating": "4.0"
 },
 {
   "brand": "PSYLO",
   "avg_brand_rating": "4.0"
 },
 {
   "brand": "Pico",
   "avg_brand_rating": "4.0"
 },
 {
   "brand": "Protean London",
   "avg_brand_rating": "4.0"
 },
 {
   "brand": "Piña",
   "avg_brand_rating": "4.0"
 },
 {
   "brand": "Puffin Gear",
   "avg_brand_rating": "3.0"
 },
 {
   "brand": "Poppie the Label",
   "avg_brand_rating": "4.0"
 },
 {
   "brand": "Pitupi",
   "avg_brand_rating": "5.0"
 },
 {
   "brand": "pinqponq",
   "avg_brand_rating": "4.0"
 },
 {
   "brand": "PLASTICITY",
   "avg_brand_rating": "4.0"
 },
 {
   "brand": "PLAYFÜL",
   "avg_brand_rating": "4.0"
 },
 {
   "brand": "POPLINEN",
   "avg_brand_rating": "4.0"
 },
 {
   "brand": "Prota Fiori",
   "avg_brand_rating": "4.0"
 },
 {
   "brand": "PRISTINE",
   "avg_brand_rating": "4.0"
 },
 {
   "brand": "Pippa Holt",
   "avg_brand_rating": "4.0"
 },
 {
   "brand": "Pleatsmama",
   "avg_brand_rating": "4.0"
 },
 {
   "brand": "Printfresh",
   "avg_brand_rating": "4.0"
 },
 {
   "brand": "Prim Stargazer",
   "avg_brand_rating": "4.0"
 },
 {
   "brand": "Puma",
   "avg_brand_rating": "4.0"
 },
 {
   "brand": "Pure Apparel",
   "avg_brand_rating": "4.0"
 },
 {
   "brand": "Polly Wales",
   "avg_brand_rating": "4.0"
 },
 {
   "brand": "Picture",
   "avg_brand_rating": "3.0"
 },
 {
   "brand": "Pure Pod",
   "avg_brand_rating": "4.0"
 },
 {
   "brand": "ReCreate",
   "avg_brand_rating": "5.0"
 },
 {
   "brand": "Reflexone",
   "avg_brand_rating": "4.0"
 },
 {
   "brand": "Recycledbags.Co",
   "avg_brand_rating": "4.0"
 },
 {
   "brand": "Real Deal Brazil",
   "avg_brand_rating": "3.0"
 },
 {
   "brand": "RÄTHEL & WOLF",
   "avg_brand_rating": "4.0"
 },
 {
   "brand": "Purnama",
   "avg_brand_rating": "4.0"
 },
 {
   "brand": "RE-BELLO",
   "avg_brand_rating": "3.0"
 },
 {
   "brand": "Purusha People",
   "avg_brand_rating": "4.0"
 },
 {
   "brand": "recolution",
   "avg_brand_rating": "4.0"
 },
 {
   "brand": "Redrew",
   "avg_brand_rating": "4.0"
 },
 {
   "brand": "Redwood Classics Apparel",
   "avg_brand_rating": "4.0"
 },
 {
   "brand": "Rentrayage",
   "avg_brand_rating": "4.0"
 },
 {
   "brand": "PYUA",
   "avg_brand_rating": "4.0"
 },
 {
   "brand": "Quazi Design",
   "avg_brand_rating": "5.0"
 },
 {
   "brand": "Rains",
   "avg_brand_rating": "3.0"
 },
 {
   "brand": "RÆBURN",
   "avg_brand_rating": "4.0"
 },
 {
   "brand": "RESAP Paris",
   "avg_brand_rating": "4.0"
 },
 {
   "brand": "Q for Quinn",
   "avg_brand_rating": "4.0"
 },
 {
   "brand": "RAANI the label",
   "avg_brand_rating": "4.0"
 },
 {
   "brand": "Rapanui",
   "avg_brand_rating": "4.0"
 },
 {
   "brand": "QWSTION",
   "avg_brand_rating": "4.0"
 },
 {
   "brand": "Rave Review",
   "avg_brand_rating": "4.0"
 },
 {
   "brand": "REEF",
   "avg_brand_rating": "3.0"
 },
 {
   "brand": "REER3",
   "avg_brand_rating": "4.0"
 },
 {
   "brand": "Qeelin",
   "avg_brand_rating": "3.0"
 },
 {
   "brand": "Pyrrha",
   "avg_brand_rating": "4.0"
 },
 {
   "brand": "Raven + Lily",
   "avg_brand_rating": "4.0"
 },
 {
   "brand": "Quincy Mae",
   "avg_brand_rating": "4.0"
 },
 {
   "brand": "S A Y A",
   "avg_brand_rating": "5.0"
 },
 {
   "brand": "RŪPAHAUS",
   "avg_brand_rating": "5.0"
 },
 {
   "brand": "RVDK",
   "avg_brand_rating": "4.0"
 },
 {
   "brand": "Salewa",
   "avg_brand_rating": "3.0"
 },
 {
   "brand": "Saana ja Olli",
   "avg_brand_rating": "4.0"
 },
 {
   "brand": "Rive Droite",
   "avg_brand_rating": "4.0"
 },
 {
   "brand": "Roberts Wood",
   "avg_brand_rating": "4.0"
 },
 {
   "brand": "Salomon",
   "avg_brand_rating": "3.0"
 },
 {
   "brand": "Safal Kids",
   "avg_brand_rating": "3.0"
 },
 {
   "brand": "RESTYLE",
   "avg_brand_rating": "4.0"
 },
 {
   "brand": "ROSE + REGGIE",
   "avg_brand_rating": "4.0"
 },
 {
   "brand": "Sage Larock",
   "avg_brand_rating": "4.0"
 },
 {
   "brand": "ReUsefulThingsStudio",
   "avg_brand_rating": "4.0"
 },
 {
   "brand": "RESIDUS",
   "avg_brand_rating": "4.0"
 },
 {
   "brand": "Ruhe",
   "avg_brand_rating": "4.0"
 },
 {
   "brand": "Saalt",
   "avg_brand_rating": "4.0"
 },
 {
   "brand": "Riley Studio",
   "avg_brand_rating": "4.0"
 },
 {
   "brand": "Rokit Vintage",
   "avg_brand_rating": "4.0"
 },
 {
   "brand": "Saint Basics",
   "avg_brand_rating": "4.0"
 },
 {
   "brand": "Salt Gypsy",
   "avg_brand_rating": "4.0"
 },
 {
   "brand": "Rotholz",
   "avg_brand_rating": "4.0"
 },
 {
   "brand": "Rice & Carry",
   "avg_brand_rating": "4.0"
 },
 {
   "brand": "Rodebjer",
   "avg_brand_rating": "3.0"
 },
 {
   "brand": "Rifò",
   "avg_brand_rating": "4.5"
 },
 {
   "brand": "Rumpl",
   "avg_brand_rating": "3.0"
 },
 {
   "brand": "S Threads Boutique",
   "avg_brand_rating": "4.0"
 },
 {
   "brand": "Sagebrush Surf Bags",
   "avg_brand_rating": "4.0"
 },
 {
   "brand": "Rowan Grey",
   "avg_brand_rating": "4.0"
 },
 {
   "brand": "Rudy Jude",
   "avg_brand_rating": "4.0"
 },
 {
   "brand": "Santos by Monica",
   "avg_brand_rating": "4.0"
 },
 {
   "brand": "Samuji",
   "avg_brand_rating": "4.0"
 },
 {
   "brand": "Sardine Clothing Company",
   "avg_brand_rating": "4.0"
 },
 {
   "brand": "Self Cinema",
   "avg_brand_rating": "4.0"
 },
 {
   "brand": "Señorita LEMONIEZ",
   "avg_brand_rating": "3.0"
 },
 {
   "brand": "SEP",
   "avg_brand_rating": "4.0"
 },
 {
   "brand": "Seea",
   "avg_brand_rating": "4.0"
 },
 {
   "brand": "SAYE",
   "avg_brand_rating": "3.0"
 },
 {
   "brand": "SeamsFriendly",
   "avg_brand_rating": "4.0"
 },
 {
   "brand": "SEEKER",
   "avg_brand_rating": "4.0"
 },
 {
   "brand": "Sami Miro Vintage",
   "avg_brand_rating": "4.0"
 },
 {
   "brand": "Sauths",
   "avg_brand_rating": "3.0"
 },
 {
   "brand": "Sarah Sue Design",
   "avg_brand_rating": "4.0"
 },
 {
   "brand": "Sealand",
   "avg_brand_rating": "5.0"
 },
 {
   "brand": "Sancho’s",
   "avg_brand_rating": "4.0"
 },
 {
   "brand": "Sense Organics",
   "avg_brand_rating": "4.0"
 },
 {
   "brand": "SEPTEMBER",
   "avg_brand_rating": "4.0"
 },
 {
   "brand": "Seek Collective",
   "avg_brand_rating": "4.0"
 },
 {
   "brand": "Seek Dry Goods",
   "avg_brand_rating": "3.0"
 },
 {
   "brand": "Salty Swimwear",
   "avg_brand_rating": "3.0"
 },
 {
   "brand": "Sasta",
   "avg_brand_rating": "3.0"
 },
 {
   "brand": "Sand Snow Linen",
   "avg_brand_rating": "4.0"
 },
 {
   "brand": "Seegarn",
   "avg_brand_rating": "4.0"
 },
 {
   "brand": "SANIKAI",
   "avg_brand_rating": "4.0"
 },
 {
   "brand": "Sans Beast",
   "avg_brand_rating": "4.0"
 },
 {
   "brand": "Seventy + Mochi",
   "avg_brand_rating": "4.0"
 },
 {
   "brand": "Savannah Morrow The Label",
   "avg_brand_rating": "3.0"
 },
 {
   "brand": "SANTICLER",
   "avg_brand_rating": "4.0"
 },
 {
   "brand": "Sandqvist",
   "avg_brand_rating": "4.0"
 },
 {
   "brand": "Solstice Kids",
   "avg_brand_rating": "4.0"
 },
 {
   "brand": "Shola Branson",
   "avg_brand_rating": "4.0"
 },
 {
   "brand": "Social Catalysts",
   "avg_brand_rating": "4.0"
 },
 {
   "brand": "Smalls Merino",
   "avg_brand_rating": "4.0"
 },
 {
   "brand": "Sotela",
   "avg_brand_rating": "4.0"
 },
 {
   "brand": "Softandwet",
   "avg_brand_rating": "4.0"
 },
 {
   "brand": "SKFK",
   "avg_brand_rating": "4.5"
 },
 {
   "brand": "Silou",
   "avg_brand_rating": "4.0"
 },
 {
   "brand": "Sinerji",
   "avg_brand_rating": "4.0"
 },
 {
   "brand": "simply grey",
   "avg_brand_rating": "3.0"
 },
 {
   "brand": "SHIBUI",
   "avg_brand_rating": "4.0"
 },
 {
   "brand": "sisam",
   "avg_brand_rating": "4.0"
 },
 {
   "brand": "SLVRLAKE",
   "avg_brand_rating": "4.0"
 },
 {
   "brand": "Sorella Organics",
   "avg_brand_rating": "4.0"
 },
 {
   "brand": "sherris",
   "avg_brand_rating": "4.0"
 },
 {
   "brand": "Shakti.ism",
   "avg_brand_rating": "4.0"
 },
 {
   "brand": "societywild",
   "avg_brand_rating": "4.0"
 },
 {
   "brand": "Smycka",
   "avg_brand_rating": "3.0"
 },
 {
   "brand": "Soleil Soleil",
   "avg_brand_rating": "5.0"
 },
 {
   "brand": "SNAP",
   "avg_brand_rating": "4.0"
 },
 {
   "brand": "Sevya",
   "avg_brand_rating": "4.0"
 },
 {
   "brand": "Sister Organics",
   "avg_brand_rating": "4.0"
 },
 {
   "brand": "soleRebels",
   "avg_brand_rating": "4.0"
 },
 {
   "brand": "Slow Stitch Studio",
   "avg_brand_rating": "4.0"
 },
 {
   "brand": "SILENT WAVE INDIGO",
   "avg_brand_rating": "5.0"
 },
 {
   "brand": "Son of a Tailor",
   "avg_brand_rating": "4.0"
 },
 {
   "brand": "Skall Studio",
   "avg_brand_rating": "4.0"
 },
 {
   "brand": "SO-LE Studio",
   "avg_brand_rating": "4.0"
 },
 {
   "brand": "SilkGenie",
   "avg_brand_rating": "5.0"
 },
 {
   "brand": "Solosix",
   "avg_brand_rating": "4.0"
 },
 {
   "brand": "STORY mfg.",
   "avg_brand_rating": "4.0"
 },
 {
   "brand": "SPELL",
   "avg_brand_rating": "4.0"
 },
 {
   "brand": "TAMGA Designs",
   "avg_brand_rating": "4.0"
 },
 {
   "brand": "Stay Wild",
   "avg_brand_rating": "4.0"
 },
 {
   "brand": "Tattered Eden",
   "avg_brand_rating": "4.0"
 },
 {
   "brand": "Sylven New York",
   "avg_brand_rating": "4.0"
 },
 {
   "brand": "Souldaze",
   "avg_brand_rating": "4.0"
 },
 {
   "brand": "SÜK Workwear",
   "avg_brand_rating": "3.0"
 },
 {
   "brand": "Sun50",
   "avg_brand_rating": "4.0"
 },
 {
   "brand": "SUI",
   "avg_brand_rating": "4.0"
 },
 {
   "brand": "SukkhaCitta",
   "avg_brand_rating": "4.0"
 },
 {
   "brand": "Stature",
   "avg_brand_rating": "4.0"
 },
 {
   "brand": "Soul Flower",
   "avg_brand_rating": "4.0"
 },
 {
   "brand": "Tasi Travels",
   "avg_brand_rating": "4.0"
 },
 {
   "brand": "Studio Courtenay",
   "avg_brand_rating": "4.0"
 },
 {
   "brand": "Swedish Stockings",
   "avg_brand_rating": "4.0"
 },
 {
   "brand": "Stephen Webster",
   "avg_brand_rating": "4.0"
 },
 {
   "brand": "Souple Luz",
   "avg_brand_rating": "4.0"
 },
 {
   "brand": "Svala",
   "avg_brand_rating": "4.0"
 },
 {
   "brand": "TALA",
   "avg_brand_rating": "3.0"
 },
 {
   "brand": "Tatti Chic",
   "avg_brand_rating": "4.0"
 },
 {
   "brand": "Talia Collins",
   "avg_brand_rating": "4.0"
 },
 {
   "brand": "Swim Against",
   "avg_brand_rating": "4.0"
 },
 {
   "brand": "Symbology",
   "avg_brand_rating": "3.0"
 },
 {
   "brand": "STANLEY/STELLA",
   "avg_brand_rating": "5.0"
 },
 {
   "brand": "Studio 189",
   "avg_brand_rating": "3.0"
 },
 {
   "brand": "Superstainable",
   "avg_brand_rating": "4.0"
 },
 {
   "brand": "Sustain by Kat",
   "avg_brand_rating": "4.0"
 },
 {
   "brand": "The Anjelms Project",
   "avg_brand_rating": "4.5"
 },
 {
   "brand": "The Blue Rabbit House",
   "avg_brand_rating": "4.0"
 },
 {
   "brand": "The Common Good Company",
   "avg_brand_rating": "5.0"
 },
 {
   "brand": "The Ethical Silk Company",
   "avg_brand_rating": "4.0"
 },
 {
   "brand": "TERAS",
   "avg_brand_rating": "4.0"
 },
 {
   "brand": "The Artful Mitten",
   "avg_brand_rating": "5.0"
 },
 {
   "brand": "Ternua",
   "avg_brand_rating": "4.0"
 },
 {
   "brand": "The Boy&I",
   "avg_brand_rating": "4.0"
 },
 {
   "brand": "The Campamento",
   "avg_brand_rating": "4.0"
 },
 {
   "brand": "The Kozm",
   "avg_brand_rating": "4.0"
 },
 {
   "brand": "TAUKO",
   "avg_brand_rating": "4.0"
 },
 {
   "brand": "Thaely",
   "avg_brand_rating": "4.0"
 },
 {
   "brand": "Terra Dea",
   "avg_brand_rating": "4.0"
 },
 {
   "brand": "Tetiana K",
   "avg_brand_rating": "3.0"
 },
 {
   "brand": "Teatum Jones",
   "avg_brand_rating": "4.0"
 },
 {
   "brand": "Terra Thread",
   "avg_brand_rating": "4.0"
 },
 {
   "brand": "The Level Collective",
   "avg_brand_rating": "4.0"
 },
 {
   "brand": "The Crafty Bird",
   "avg_brand_rating": "3.0"
 },
 {
   "brand": "The Knotty Ones",
   "avg_brand_rating": "4.0"
 },
 {
   "brand": "The bonnie mob",
   "avg_brand_rating": "4.0"
 },
 {
   "brand": "tehadesigns",
   "avg_brand_rating": "4.0"
 },
 {
   "brand": "The Blue Suit",
   "avg_brand_rating": "5.0"
 },
 {
   "brand": "Tekla",
   "avg_brand_rating": "4.0"
 },
 {
   "brand": "Teva",
   "avg_brand_rating": "3.0"
 },
 {
   "brand": "Tiger Prints",
   "avg_brand_rating": "4.0"
 },
 {
   "brand": "The Recycled Planet",
   "avg_brand_rating": "3.0"
 },
 {
   "brand": "Théla",
   "avg_brand_rating": "5.0"
 },
 {
   "brand": "The White Briefs",
   "avg_brand_rating": "4.0"
 },
 {
   "brand": "The Rushing Hour",
   "avg_brand_rating": "4.0"
 },
 {
   "brand": "Thunderpants USA",
   "avg_brand_rating": "5.0"
 },
 {
   "brand": "The R Collective",
   "avg_brand_rating": "5.0"
 },
 {
   "brand": "Thesus",
   "avg_brand_rating": "4.0"
 },
 {
   "brand": "The Standard Stitch",
   "avg_brand_rating": "5.0"
 },
 {
   "brand": "This is Unfolded",
   "avg_brand_rating": "4.0"
 },
 {
   "brand": "The Maker Collection",
   "avg_brand_rating": "4.0"
 },
 {
   "brand": "THE MORPHBAG BY GSK",
   "avg_brand_rating": "4.0"
 },
 {
   "brand": "Threads 4 Thought",
   "avg_brand_rating": "4.0"
 },
 {
   "brand": "The Moonrise Project",
   "avg_brand_rating": "4.0"
 },
 {
   "brand": "THEA WITH LOVE",
   "avg_brand_rating": "3.0"
 },
 {
   "brand": "The Social Outfit",
   "avg_brand_rating": "4.0"
 },
 {
   "brand": "Thunderpants NZ",
   "avg_brand_rating": "5.0"
 },
 {
   "brand": "The Very Good Bra",
   "avg_brand_rating": "4.0"
 },
 {
   "brand": "The Social Studio",
   "avg_brand_rating": "5.0"
 },
 {
   "brand": "The Spotted Quoll Studio",
   "avg_brand_rating": "4.0"
 },
 {
   "brand": "ThokkThokk",
   "avg_brand_rating": "4.0"
 },
 {
   "brand": "The SUSS Edit",
   "avg_brand_rating": "4.0"
 },
 {
   "brand": "The Summer House",
   "avg_brand_rating": "4.0"
 },
 {
   "brand": "The White Ribbon",
   "avg_brand_rating": "4.0"
 },
 {
   "brand": "The North Face",
   "avg_brand_rating": "3.5"
 },
 {
   "brand": "Thought",
   "avg_brand_rating": "3.0"
 },
 {
   "brand": "Thief&Bandit",
   "avg_brand_rating": "4.0"
 },
 {
   "brand": "The Tiny Closet",
   "avg_brand_rating": "5.0"
 },
 {
   "brand": "Thinking MU",
   "avg_brand_rating": "4.0"
 },
 {
   "brand": "Think Big Little People",
   "avg_brand_rating": "4.0"
 },
 {
   "brand": "Toby Tiger",
   "avg_brand_rating": "4.0"
 },
 {
   "brand": "Tultex",
   "avg_brand_rating": "3.0"
 },
 {
   "brand": "Tzoma",
   "avg_brand_rating": "4.0"
 },
 {
   "brand": "Tiny Twig",
   "avg_brand_rating": "4.0"
 },
 {
   "brand": "Tivoli",
   "avg_brand_rating": "4.0"
 },
 {
   "brand": "Two Sparrow Australia",
   "avg_brand_rating": "4.0"
 },
 {
   "brand": "Treekid",
   "avg_brand_rating": "4.5"
 },
 {
   "brand": "Tuckerman & Co",
   "avg_brand_rating": "4.0"
 },
 {
   "brand": "True Tribe",
   "avg_brand_rating": "4.0"
 },
 {
   "brand": "Timberland",
   "avg_brand_rating": "4.0"
 },
 {
   "brand": "Tree of Life",
   "avg_brand_rating": "3.0"
 },
 {
   "brand": "Touch Me Not",
   "avg_brand_rating": "4.0"
 },
 {
   "brand": "Twofold Clothing",
   "avg_brand_rating": "4.0"
 },
 {
   "brand": "TWOTHIRDS",
   "avg_brand_rating": "4.0"
 },
 {
   "brand": "Toit Volant",
   "avg_brand_rating": "3.0"
 },
 {
   "brand": "Tomorrow Denim",
   "avg_brand_rating": "4.0"
 },
 {
   "brand": "Tommy & Lottie",
   "avg_brand_rating": "4.0"
 },
 {
   "brand": "Tri Colour Federation",
   "avg_brand_rating": "4.0"
 },
 {
   "brand": "Tortoise The Label",
   "avg_brand_rating": "4.0"
 },
 {
   "brand": "Tropicfeel",
   "avg_brand_rating": "3.0"
 },
 {
   "brand": "Two Little Beans & Co",
   "avg_brand_rating": "3.0"
 },
 {
   "brand": "Tomo & Edie",
   "avg_brand_rating": "4.0"
 },
 {
   "brand": "TRENDY STREET",
   "avg_brand_rating": "4.0"
 },
 {
   "brand": "Titania Inglis",
   "avg_brand_rating": "3.0"
 },
 {
   "brand": "Turtledove London",
   "avg_brand_rating": "4.0"
 },
 {
   "brand": "Tripulse",
   "avg_brand_rating": "4.5"
 },
 {
   "brand": "U-MASK",
   "avg_brand_rating": "4.0"
 },
 {
   "brand": "Tread & Butter",
   "avg_brand_rating": "3.0"
 },
 {
   "brand": "Under The Nile",
   "avg_brand_rating": "4.0"
 },
 {
   "brand": "VATTER",
   "avg_brand_rating": "5.0"
 },
 {
   "brand": "Variety Hour",
   "avg_brand_rating": "4.0"
 },
 {
   "brand": "Unrecorded",
   "avg_brand_rating": "4.0"
 },
 {
   "brand": "Ulalü",
   "avg_brand_rating": "4.0"
 },
 {
   "brand": "UndeadMagpie",
   "avg_brand_rating": "4.0"
 },
 {
   "brand": "Untouched World",
   "avg_brand_rating": "4.0"
 },
 {
   "brand": "Ucon Acrobatics",
   "avg_brand_rating": "4.0"
 },
 {
   "brand": "VAUDE",
   "avg_brand_rating": "4.0"
 },
 {
   "brand": "Velocio",
   "avg_brand_rating": "4.0"
 },
 {
   "brand": "Underprotection",
   "avg_brand_rating": "4.0"
 },
 {
   "brand": "Velvet Heartbeat",
   "avg_brand_rating": "4.0"
 },
 {
   "brand": "Uskees",
   "avg_brand_rating": "4.0"
 },
 {
   "brand": "VENIM",
   "avg_brand_rating": "4.0"
 },
 {
   "brand": "Vernisse",
   "avg_brand_rating": "4.0"
 },
 {
   "brand": "Unrobe",
   "avg_brand_rating": "5.0"
 },
 {
   "brand": "Vanina",
   "avg_brand_rating": "4.0"
 },
 {
   "brand": "VegasRabbitClothing",
   "avg_brand_rating": "5.0"
 },
 {
   "brand": "UNOA",
   "avg_brand_rating": "4.0"
 },
 {
   "brand": "US Blanks",
   "avg_brand_rating": "3.0"
 },
 {
   "brand": "VEERAH",
   "avg_brand_rating": "4.0"
 },
 {
   "brand": "Vege Threads",
   "avg_brand_rating": "4.0"
 },
 {
   "brand": "Untold Jewellery",
   "avg_brand_rating": "4.0"
 },
 {
   "brand": "Ukiyo",
   "avg_brand_rating": "3.0"
 },
 {
   "brand": "Unbelts",
   "avg_brand_rating": "4.0"
 },
 {
   "brand": "Vesica Piscis",
   "avg_brand_rating": "4.0"
 },
 {
   "brand": "Will’s Vegan Store",
   "avg_brand_rating": "4.0"
 },
 {
   "brand": "Wear Your Love",
   "avg_brand_rating": "3.0"
 },
 {
   "brand": "VRAI",
   "avg_brand_rating": "4.0"
 },
 {
   "brand": "Virón",
   "avg_brand_rating": "4.0"
 },
 {
   "brand": "WAMA",
   "avg_brand_rating": "4.0"
 },
 {
   "brand": "Vild House of Little",
   "avg_brand_rating": "4.0"
 },
 {
   "brand": "WE-AR4",
   "avg_brand_rating": "4.0"
 },
 {
   "brand": "von Holzhausen",
   "avg_brand_rating": "4.0"
 },
 {
   "brand": "wayre",
   "avg_brand_rating": "4.0"
 },
 {
   "brand": "Wemoto",
   "avg_brand_rating": "3.0"
 },
 {
   "brand": "Vietopia",
   "avg_brand_rating": "4.0"
 },
 {
   "brand": "Wellicious",
   "avg_brand_rating": "3.0"
 },
 {
   "brand": "Vitamin A",
   "avg_brand_rating": "4.0"
 },
 {
   "brand": "Wild Country",
   "avg_brand_rating": "3.0"
 },
 {
   "brand": "WAWWA",
   "avg_brand_rating": "4.0"
 },
 {
   "brand": "WALD Berlin",
   "avg_brand_rating": "4.0"
 },
 {
   "brand": "WalkinThroughFlowers",
   "avg_brand_rating": "5.0"
 },
 {
   "brand": "West Activewear",
   "avg_brand_rating": "3.0"
 },
 {
   "brand": "village thrive",
   "avg_brand_rating": "4.0"
 },
 {
   "brand": "VYAYAMA",
   "avg_brand_rating": "3.0"
 },
 {
   "brand": "VOIT",
   "avg_brand_rating": "3.0"
 },
 {
   "brand": "Wildflo Studio",
   "avg_brand_rating": "4.0"
 },
 {
   "brand": "Wildling",
   "avg_brand_rating": "4.0"
 },
 {
   "brand": "Vigo Swim",
   "avg_brand_rating": "4.0"
 },
 {
   "brand": "Viverano",
   "avg_brand_rating": "4.0"
 },
 {
   "brand": "WeAreNativ",
   "avg_brand_rating": "4.0"
 },
 {
   "brand": "Wilson and Frenchy",
   "avg_brand_rating": "3.0"
 },
 {
   "brand": "Where Does It Come From?",
   "avg_brand_rating": "5.0"
 },
 {
   "brand": "WACCOWACCO",
   "avg_brand_rating": "4.0"
 },
 {
   "brand": "ZUZU & CO",
   "avg_brand_rating": "4.0"
 },
 {
   "brand": "WUF KIDS",
   "avg_brand_rating": "4.0"
 },
 {
   "brand": "Yuki Threads",
   "avg_brand_rating": "4.0"
 },
 {
   "brand": "WWAKE",
   "avg_brand_rating": "4.0"
 },
 {
   "brand": "wunderwerk",
   "avg_brand_rating": "4.0"
 },
 {
   "brand": "宝島染工 / Takarajima Senkou",
   "avg_brand_rating": "4.0"
 },
 {
   "brand": "XZOUIX",
   "avg_brand_rating": "4.0"
 },
 {
   "brand": "Yes And",
   "avg_brand_rating": "4.0"
 },
 {
   "brand": "Yes Friends",
   "avg_brand_rating": "5.0"
 },
 {
   "brand": "Yanawara",
   "avg_brand_rating": "4.0"
 },
 {
   "brand": "YU STEPANEL",
   "avg_brand_rating": "4.0"
 },
 {
   "brand": "Zazi",
   "avg_brand_rating": "4.0"
 },
 {
   "brand": "Zuri",
   "avg_brand_rating": "4.0"
 },
 {
   "brand": "Wuxly Movement",
   "avg_brand_rating": "4.0"
 },
 {
   "brand": "Wolf and Zephyr",
   "avg_brand_rating": "4.0"
 },
 {
   "brand": "Windsor Lane",
   "avg_brand_rating": "4.0"
 },
 {
   "brand": "Woron",
   "avg_brand_rating": "4.0"
 },
 {
   "brand": "Zulu & Zephyr",
   "avg_brand_rating": "4.0"
 },
 {
   "brand": "Wires",
   "avg_brand_rating": "4.0"
 },
 {
   "brand": "Wyatt and Jack",
   "avg_brand_rating": "4.0"
 },
 {
   "brand": "Zilver",
   "avg_brand_rating": "4.0"
 },
 {
   "brand": "Y.O.U Underwear",
   "avg_brand_rating": "5.0"
 },
 {
   "brand": "Womsh",
   "avg_brand_rating": "4.0"
 },
 {
   "brand": "Winter Water Factory",
   "avg_brand_rating": "4.0"
 },
 {
   "brand": "YoRo Naturals",
   "avg_brand_rating": "4.0"
 },
 {
   "brand": "Wouf",
   "avg_brand_rating": "4.0"
 },
 {
   "brand": "ZEROBARRACENTO",
   "avg_brand_rating": "4.0"
 },
 {
   "brand": "World Of Crow",
   "avg_brand_rating": "4.0"
 },
 {
   "brand": "石徹白洋品店 / Itoshiro Yohinten",
   "avg_brand_rating": "4.0"
 },
 {
   "brand": "Princess Polly",
   "avg_brand_rating": "2.0"
 },
 {
   "brand": "Brandy Melville",
   "avg_brand_rating": "1.0"
 },
 {
   "brand": "Shein",
   "avg_brand_rating": "1.0"
 },
 {
   "brand": "Abercrombie & Fitch",
   "avg_brand_rating": "2.0"
 },
 {
   "brand": "Amazon",
   "avg_brand_rating": "2.0"
 },
 {
   "brand": "ASOS",
   "avg_brand_rating": "2.0"
 },
 {
   "brand": "Forever 21",
   "avg_brand_rating": "1.0"
 },
 {
   "brand": "American Eagle",
   "avg_brand_rating": "2.0"
 },
 {
   "brand": "Alo",
   "avg_brand_rating": "1.0"
 },
 {
   "brand": "Acne Studios",
   "avg_brand_rating": "3.0"
 },
 {
   "brand": "Alice + Olivia",
   "avg_brand_rating": "1.0"
 },
 {
   "brand": "Sandy Liang",
   "avg_brand_rating": "2.0"
 },
 {
   "brand": "Billabong",
   "avg_brand_rating": "2.0"
 },
 {
   "brand": "Aritzia",
   "avg_brand_rating": "2.0"
 },
 {
   "brand": "Uniqlo",
   "avg_brand_rating": "3.0"
 },
 {
   "brand": "Area",
   "avg_brand_rating": "2.0"
 },
 {
   "brand": "Bottega Veneta",
   "avg_brand_rating": "3.0"
 },
 {
   "brand": "Brooks Brothers",
   "avg_brand_rating": "1.0"
 },
 {
   "brand": "Burberry",
   "avg_brand_rating": "3.0"
 },
 {
   "brand": "Chanel",
   "avg_brand_rating": "2.0"
 },
 {
   "brand": "Coach",
   "avg_brand_rating": "2.0"
 },
 {
   "brand": "Fendi",
   "avg_brand_rating": "2.0"
 },
 {
   "brand": "Gucci",
   "avg_brand_rating": "3.0"
 },
 {
   "brand": "Hermes",
   "avg_brand_rating": "2.0"
 },
 {
   "brand": "Louis Vuitton",
   "avg_brand_rating": "2.0"
 },
 {
   "brand": "Prada",
   "avg_brand_rating": "2.0"
 },
 {
   "brand": "Ralph Lauren",
   "avg_brand_rating": "2.0"
 },
 {
   "brand": "Saint Laurent",
   "avg_brand_rating": "3.0"
 },
 {
   "brand": "Telfar",
   "avg_brand_rating": "1.0"
 },
 {
   "brand": "The Row",
   "avg_brand_rating": "1.0"
 },
 {
   "brand": "Theory",
   "avg_brand_rating": "2.0"
 },
 {
   "brand": "Tom Ford",
   "avg_brand_rating": "1.0"
 },
 {
   "brand": "Tory Burch",
   "avg_brand_rating": "1.0"
 },
 {
   "brand": "Valentino",
   "avg_brand_rating": "2.0"
 },
 {
   "brand": "7 For All Mankind",
   "avg_brand_rating": "2.0"
 },
 {
   "brand": "Banana Republic",
   "avg_brand_rating": "2.0"
 },
 {
   "brand": "Boden",
   "avg_brand_rating": "2.0"
 },
 {
   "brand": "Buck Mason",
   "avg_brand_rating": "2.0"
 },
 {
   "brand": "Calvin Klein",
   "avg_brand_rating": "2.0"
 },
 {
   "brand": "Carhartt",
   "avg_brand_rating": "2.0"
 },
 {
   "brand": "Columbia",
   "avg_brand_rating": "2.0"
 },
 {
   "brand": "Djerf Avenue",
   "avg_brand_rating": "3.0"
 },
 {
   "brand": "Doen",
   "avg_brand_rating": "3.0"
 },
 {
   "brand": "Edikted",
   "avg_brand_rating": "1.0"
 },
 {
   "brand": "Everlane",
   "avg_brand_rating": "3.0"
 },
 {
   "brand": "Frankies Bikinis",
   "avg_brand_rating": "2.0"
 },
 {
   "brand": "Good American",
   "avg_brand_rating": "1.0"
 },
 {
   "brand": "House of Sunny",
   "avg_brand_rating": "2.0"
 },
 {
   "brand": "J.Crew",
   "avg_brand_rating": "2.0"
 },
 {
   "brand": "Levi's",
   "avg_brand_rating": "3.0"
 },
 {
   "brand": "Madewell",
   "avg_brand_rating": "2.0"
 },
 {
   "brand": "Quince",
   "avg_brand_rating": "2.0"
 },
 {
   "brand": "RE/DONE",
   "avg_brand_rating": "2.0"
 },
 {
   "brand": "Réalisation Par",
   "avg_brand_rating": "1.0"
 },
 {
   "brand": "REI",
   "avg_brand_rating": "2.0"
 },
 {
   "brand": "Sezane",
   "avg_brand_rating": "2.0"
 },
 {
   "brand": "Summersalt",
   "avg_brand_rating": "2.0"
 },
 {
   "brand": "Tommy Hilfiger",
   "avg_brand_rating": "2.0"
 },
 {
   "brand": "True Religion",
   "avg_brand_rating": "1.0"
 },
 {
   "brand": "Wrangler",
   "avg_brand_rating": "2.0"
 },
 {
   "brand": "Aeropostale",
   "avg_brand_rating": "1.0"
 },
 {
   "brand": "Boohoo",
   "avg_brand_rating": "2.0"
 },
 {
   "brand": "Cider",
   "avg_brand_rating": "1.0"
 },
 {
   "brand": "Fashion Nova",
   "avg_brand_rating": "1.0"
 },
 {
   "brand": "GUESS",
   "avg_brand_rating": "2.0"
 },
 {
   "brand": "Hollister",
   "avg_brand_rating": "2.0"
 },
 {
   "brand": "Hot Topic",
   "avg_brand_rating": "1.0"
 },
 {
   "brand": "House of CB",
   "avg_brand_rating": "1.0"
 },
 {
   "brand": "Mango",
   "avg_brand_rating": "2.0"
 },
 {
   "brand": "Missguided",
   "avg_brand_rating": "1.0"
 },
 {
   "brand": "Nasty Gal",
   "avg_brand_rating": "2.0"
 },
 {
   "brand": "PacSun",
   "avg_brand_rating": "1.0"
 },
 {
   "brand": "PrettyLittleThing",
   "avg_brand_rating": "2.0"
 },
 {
   "brand": "Primark",
   "avg_brand_rating": "2.0"
 },
 {
   "brand": "Romwe",
   "avg_brand_rating": "1.0"
 },
 {
   "brand": "Temu",
   "avg_brand_rating": "1.0"
 },
 {
   "brand": "Topshop",
   "avg_brand_rating": "2.0"
 },
 {
   "brand": "Torrid",
   "avg_brand_rating": "1.0"
 },
 {
   "brand": "Under Armour",
   "avg_brand_rating": "2.0"
 },
 {
   "brand": "Victoria's Secret",
   "avg_brand_rating": "2.0"
 },
 {
   "brand": "Yesstyle",
   "avg_brand_rating": "1.0"
 },
 {
   "brand": "Ann Taylor",
   "avg_brand_rating": "2.0"
 },
 {
   "brand": "Aerie",
   "avg_brand_rating": "2.0"
 },
 {
   "brand": "Garage",
   "avg_brand_rating": "2.0"
 },
 {
   "brand": "Pink",
   "avg_brand_rating": "2.0"
 },
 {
   "brand": "Esprit",
   "avg_brand_rating": "3.0"
 },
 {
   "brand": "LOVETRUST",
   "avg_brand_rating": "4.0"
 },
 {
   "brand": "Yoga Democracy",
   "avg_brand_rating": "3.0"
 },
 {
   "brand": "京和晒綿紗 / kyowazarashi mensha",
   "avg_brand_rating": "3.0"
 },
 {
   "brand": "Holzweiler",
   "avg_brand_rating": "3.0"
 },
 {
   "brand": "Isadore Apparel",
   "avg_brand_rating": "3.0"
 },
 {
   "brand": "Kathmandu",
   "avg_brand_rating": "3.0"
 },
 {
   "brand": "Peak Performance",
   "avg_brand_rating": "3.0"
 },
 {
   "brand": "MORI",
   "avg_brand_rating": "3.0"
 },
 {
   "brand": "BJ’s PJ’s",
   "avg_brand_rating": "4.0"
 },
 {
   "brand": "Owlivia",
   "avg_brand_rating": "3.0"
 },
 {
   "brand": "MARUPE LINEN HOUSE",
   "avg_brand_rating": "3.0"
 },
 {
   "brand": "Fruit of the Loom",
   "avg_brand_rating": "3.0"
 },
 {
   "brand": "Maya Eco",
   "avg_brand_rating": "3.0"
 },
 {
   "brand": "Silq Rose",
   "avg_brand_rating": "3.0"
 },
 {
   "brand": "Mummelito",
   "avg_brand_rating": "3.0"
 },
 {
   "brand": "Geggamoja",
   "avg_brand_rating": "3.0"
 },
 {
   "brand": "Rock On Ruby",
   "avg_brand_rating": "3.0"
 },
 {
   "brand": "menique",
   "avg_brand_rating": "3.0"
 },
 {
   "brand": "Dagsmejan",
   "avg_brand_rating": "3.0"
 },
 {
   "brand": "Loom",
   "avg_brand_rating": "4.0"
 },
 {
   "brand": "The Madison Collection",
   "avg_brand_rating": "3.0"
 },
 {
   "brand": "Y-3",
   "avg_brand_rating": "3.0"
 },
 {
   "brand": "Le Slip Français",
   "avg_brand_rating": "3.0"
 },
 {
   "brand": "UGG",
   "avg_brand_rating": "3.0"
 },
 {
   "brand": "Lelasilk",
   "avg_brand_rating": "3.0"
 },
 {
   "brand": "Merino Kids",
   "avg_brand_rating": "3.0"
 },
 {
   "brand": "LesJour!",
   "avg_brand_rating": "3.0"
 },
 {
   "brand": "Setup",
   "avg_brand_rating": "3.0"
 },
 {
   "brand": "Eco Tee Co",
   "avg_brand_rating": "3.0"
 },
 {
   "brand": "Hēdoïne",
   "avg_brand_rating": "3.0"
 },
 {
   "brand": "Organically",
   "avg_brand_rating": "3.0"
 },
 {
   "brand": "Le Gramme",
   "avg_brand_rating": "3.0"
 },
 {
   "brand": "Derbe",
   "avg_brand_rating": "4.0"
 },
 {
   "brand": "Accel Lifestyle",
   "avg_brand_rating": "3.0"
 },
 {
   "brand": "Smartwool",
   "avg_brand_rating": "3.0"
 },
 {
   "brand": "WAXON",
   "avg_brand_rating": "4.0"
 },
 {
   "brand": "GU",
   "avg_brand_rating": "3.0"
 },
 {
   "brand": "Bedhead Pajamas",
   "avg_brand_rating": "3.0"
 },
 {
   "brand": "Wallace Cotton",
   "avg_brand_rating": "3.0"
 },
 {
   "brand": "MANOLA",
   "avg_brand_rating": "3.0"
 },
 {
   "brand": "Kat The Label",
   "avg_brand_rating": "3.0"
 },
 {
   "brand": "Earth Baby Outfitters",
   "avg_brand_rating": "3.0"
 },
 {
   "brand": "GILDA & PEARL",
   "avg_brand_rating": "3.0"
 },
 {
   "brand": "Maylyn & Co.",
   "avg_brand_rating": "3.0"
 },
 {
   "brand": "les girls les boys",
   "avg_brand_rating": "3.0"
 },
 {
   "brand": "CDLP",
   "avg_brand_rating": "3.0"
 },
 {
   "brand": "MORALFIBRE",
   "avg_brand_rating": "3.0"
 },
 {
   "brand": "DUE.",
   "avg_brand_rating": "3.0"
 },
 {
   "brand": "Loulou Lollipop",
   "avg_brand_rating": "3.0"
 },
 {
   "brand": "Barta Jeans",
   "avg_brand_rating": "4.0"
 },
 {
   "brand": "Viktoria and Woods",
   "avg_brand_rating": "3.0"
 },
 {
   "brand": "Royal Apparel",
   "avg_brand_rating": "3.0"
 },
 {
   "brand": "MPG Sport",
   "avg_brand_rating": "3.0"
 },
 {
   "brand": "From The Heart",
   "avg_brand_rating": "4.0"
 },
 {
   "brand": "BELLA+CANVAS",
   "avg_brand_rating": "3.0"
 },
 {
   "brand": "Polarn O. Pyret",
   "avg_brand_rating": "3.0"
 },
 {
   "brand": "Hamilton and Hare",
   "avg_brand_rating": "3.0"
 },
 {
   "brand": "Xiao Wang",
   "avg_brand_rating": "3.0"
 },
 {
   "brand": "Message Factory",
   "avg_brand_rating": "4.0"
 },
 {
   "brand": "We Are HAH",
   "avg_brand_rating": "3.0"
 },
 {
   "brand": "Erin Snow",
   "avg_brand_rating": "3.0"
 },
 {
   "brand": "Macpac",
   "avg_brand_rating": "3.0"
 },
 {
   "brand": "Pour Les Femmes",
   "avg_brand_rating": "3.0"
 },
 {
   "brand": "Princesse tam.tam",
   "avg_brand_rating": "3.0"
 }
]